Workbook
Name Discount_Table: 'Master Sheet'!$B$2:$C$12
Name NativeTimeline_Order_Date1: #N/A
Name Product_Assign: 'Master Sheet'!$E$3:$F$9
Name Region_Table: 'Master Sheet'!$E$16:$F$22
Name Slicer_Brand_Name: #N/A
Name Slicer_City: #N/A
Name Slicer_Dealer_Name1: #N/A
Name Slicer_Region1: #N/A
Name Slicer_State: #N/A
Name Slicer_Tractor_Model: #N/A
Name Table_2: Table1[#All]

Sheet Raw_Sales_Data
A1: Invoice ID | B1: Order Date | C1: Dealer Name | D1: State | E1: City | F1: Region | G1: Sales Executive | H1: Tractor Model | I1: Quantity | J1: Unit Price | K1: Discount % | L1: Sales Amount | M1: Payment Status | N1: Delivery Status | O1: GST Status | P1: Order Status
A2: INV1000 | B2: 2024/04/23 | C2: Shakti Agro | D2: UP | E2: Lucknow | F2: North | G2: NEHA | H2: Farmtrac 60 | I2: 1 | J2: 810386 | K2: 0 | L2: 810386 | M2: Partial | N2: Cancelled | O2: Invalid | P2: Cancelled
A3: INV1001 | B3: 2024/02/04 | C3: Shakti Agro | D3: Karnataka | E3: Bengaluru | F3: South | G3: Priya | H3: Kubota MU4501 | I3: 6 | J3: 421642 | K3: 5 | L3: 2403359.4 | M3: Partial | N3: Cancelled | O3: Invalid | P3: Cancelled
A4: INV1002 | B4: 2024/12/31 | C4: Green Field | D4: Maharashtra | E4: Pune | F4: West | G4: Amit | H4: Kubota MU4501 | I4: 7 | J4: 58962 | K4: 0 | L4: 412734 | M4: Pending | N4: Delivered | O4: Valid | P4: Cancelled
A5: INV1003 | B5: 09/15/2024 | C5: Green Field | D5: Haryana | E5: Gurugram | F5: North | G5: Priya | H5: Kubota MU4501 | I5: 7 | J5: 640018 | K5: 10 | L5: 4032113.4 | M5: Partial | N5: Delivered | O5: Valid | P5: Pending
A6: INV1004 | B6: 28-05-2025 | C6: Shakti Agro | D6: haryana | E6: Gurugram | F6: North | G6: Neha | H6: Farmtrac 45 | I6: 2 | J6: 736528 | K6: 10 | L6: 1325750.4 | M6: Paid | N6: Delivered | O6: Invalid | P6: Completed
A7: INV1005 | B7: 27-03-2025 | C7: Green Field | D7: UP | E7: Lucknow | F7: North | G7: Amit | H7: Powertrac 439 | I7: 3 | J7: 446618 | K7: 2 | L7: 1313056.9 | M7: Pending | N7: Delivered | O7: Invalid | P7: Completed
A8: INV1006 | B8: 09-10-2024 | C8: Green Field | D8: Maharashtra | E8: Pune | F8: West | G8: Vikas | H8: Powertrac 439 | I8: 4 | J8: 636846 | K8: 7 | L8: 2369067.1 | M8: Partial | N8: Delivered | O8: Invalid | P8: Cancelled
A9: INV1007 | B9: 17-11-2024 | C9: Kisan Tractors | D9: West Bengal | E9: Kolkata | F9: East | G9: Neha | H9: Farmtrac 45 | I9: 4 | J9: 87171 | K9: 5 | L9: 331249.8 | M9: Pending | N9: In Transit | O9: Valid | P9: Completed
A10: INV1008 | B10: 09-11-2024 | C10: Kisan Tractors | D10: Haryana | E10: Gurugram | F10: North | G10: Rohit | H10: Kubota MU4501 | I10: 6 | J10: 435799 | K10: 7 | L10: 2431758.4 | M10: Paid | N10: Delivered | O10: Valid | P10: Completed
A11: INV1009 | B11: 23-11-2024 | C11: Mahadev Motors | D11: Karnataka | E11: Bengaluru | F11: South | G11: Priya | H11: Farmtrac 45 | I11: 3 | J11: 91771 | K11: 12 | L11: 242275.44 | M11: Paid | N11: In Transit | O11: Valid | P11: Cancelled
A12: INV1010 | B12: 2024/02/07 | C12: Mahadev Motors | D12: UP | E12: Lucknow | F12: North | G12: NEHA | H12: Powertrac 439 | I12: 1 | J12: 366788 | K12: 2 | L12: 359452.24 | M12: Partial | N12: In Transit | O12: Invalid | P12: Completed
A13: INV1011 | B13: 16-01-2025 | C13: Kisan Tractors | D13: West Bengal | E13: Kolkata | F13: East | G13: Rohit | H13: Powertrac 439 | I13: 8 | J13: 745852 | K13: 0 | L13: 5966816 | M13: Paid | N13: Delivered | O13: Valid | P13: Pending
... A61: INV1059 | B61: 08/21/2024 | C61: Shakti Agro | D61: UP | E61: Lucknow | F61: North | G61: Priya | H61: Powertrac 439 | I61: 5 | J61: 501803 | K61: 2 | L61: 2458834.7 | M61: Paid | N61: Delivered | O61: Valid | P61: Pending
A62: INV1060 | B62: 12/15/2024 | C62: Agri Motors | D62: Haryana | E62: Gurugram | F62: North | G62: ROHIT | H62: Farmtrac 60 | J62: 652887 | K62: 10 | M62: Partial | N62: Delivered | O62: Invalid | P62: Completed
A63: INV1061 | B63: 2024/07/21 | C63: Shakti Agro | D63: Maharashtra | E63: Pune | F63: West | G63: VIKAS | H63: Kubota NeoStar | J63: 526133 | K63: 10 | M63: Pending | N63: Cancelled | O63: Invalid | P63: Pending
A64: INV1062 | B64: 04-01-2025 | C64: Green Field | D64: Haryana | E64: Gurugram | F64: North | G64: Vikas | H64: Powertrac 439 | I64: 5 | J64: 711154 | K64: 0 | L64: 3555770 | M64: Paid | N64: Delivered | O64: Valid | P64: Completed
A65: INV1063 | B65: 2024/11/06 | C65: Shakti Agro | D65: Haryana | E65: Gurugram | F65: North | G65: Priya | H65: Farmtrac 45 | I65: 4 | J65: 105885 | K65: 2 | L65: 415069.2 | M65: Pending | N65: Delivered | O65: Invalid | P65: Pending
A66: INV1064 | B66: 17-10-2024 | C66: Agri Motors | D66: West Bengal | E66: Kolkata | F66: East | G66: Vikas | H66: Farmtrac 60 | I66: 1 | J66: 618459 | K66: 5 | L66: 587536.05 | M66: Pending | N66: Delivered | O66: Invalid | P66: Completed
A67: INV1065 | B67: 10/18/2024 | C67: Agri Motors | D67: West Bengal | E67: Kolkata | F67: East | G67: Priya | H67: Farmtrac 45 | I67: 6 | J67: 74760 | K67: 12 | L67: 394732.8 | M67: Pending | N67: Delivered | O67: Invalid | P67: Cancelled
A68: INV1066 | B68: 08-02-2025 | C68: Mahadev Motors | D68: Karnataka | E68: Bengaluru | F68: South | G68: Neha | H68: Farmtrac 45 | I68: 5 | J68: 50674 | K68: 7 | L68: 235634.1 | M68: Partial | N68: Cancelled | O68: Invalid | P68: Pending
A69: INV1067 | B69: 06/21/2025 | C69: Shakti Agro | D69: Maharashtra | E69: Pune | F69: West | G69: Neha | H69: Kubota MU4501 | I69: 2 | J69: 832128 | K69: 5 | L69: 1581043.2 | M69: Pending | N69: In Transit | O69: Invalid | P69: Cancelled
A70: INV1068 | B70: 12/02/2024 | C70: Kisan Tractors | D70: Maharashtra | E70: Pune | F70: West | G70: Rohit | H70: Kubota MU4501 | I70: 4 | J70: 866057 | K70: 5 | L70: 3291016.6 | M70: Paid | N70: In Transit | O70: Valid | P70: Pending
A71: INV1069 | B71: 16-02-2024 | C71: Kisan Tractors | D71: Maharashtra | E71: Pune | F71: West | G71: Neha | H71: Farmtrac 45 | I71: 3 | J71: 653046 | K71: 0 | L71: 1959138 | M71: Pending | N71: In Transit | O71: Valid | P71: Pending
A72: INV1070 | B72: 2025/06/14 | C72: Shakti Agro | D72: Maharashtra | E72: Pune | F72: West | G72: Rohit | H72: Farmtrac 45 | I72: 7 | J72: 516456 | K72: 12 | L72: 3181369 | M72: Paid | N72: Cancelled | O72: Valid | P72: Completed
A73: INV1071 | B73: 11/21/2024 | C73: Agri Motors | D73: west bengal | E73: Kolkata | F73: East | G73: Amit | H73: Powertrac 439 | I73: 4 | J73: 745689 | K73: 5 | L73: 2833618.2 | M73: Partial | N73: Cancelled | O73: Invalid | P73: Pending
A74: INV1072 | B74: 2024/01/27 | C74: Kisan Tractors | D74: haryana | E74: Gurugram | F74: North | G74: Rohit | H74: Powertrac 439 | I74: 5 | J74: 127757 | M74: Pending | N74: Cancelled | O74: Invalid | P74: Pending
A75: INV1073 | B75: 19-11-2024 | C75: Mahadev Motors | D75: West Bengal | E75: Kolkata | F75: East | G75: Rohit | H75: Farmtrac 60 | I75: 8 | J75: 260553 | K75: 10 | L75: 1875981.6 | M75: Pending | N75: In Transit | O75: Invalid | P75: Completed
A76: INV1074 | B76: 04/25/2025 | C76: Agri Motors | D76: UP | E76: Lucknow | F76: North | G76: Amit | H76: Kubota MU4501 | I76: 2 | J76: 420146 | K76: 2 | L76: 823486.16 | M76: Paid | N76: In Transit | O76: Invalid | P76: Pending
A77: INV1075 | B77: 04/21/2024 | C77: Agri Motors | D77: UP | E77: Lucknow | F77: North | G77: Rohit | H77: Farmtrac 60 | I77: 8 | J77: 267590 | K77: 7 | L77: 1990869.6 | M77: Paid | N77: In Transit | O77: Invalid | P77: Pending
A78: INV1076 | B78: 09/23/2024 | C78: Mahadev Motors | D78: West Bengal | E78: Kolkata | F78: East | G78: Rohit | H78: Kubota MU4501 | I78: 8 | J78: 100872 | K78: 0 | L78: 806976 | M78: Partial | N78: Delivered | O78: Valid | P78: Pending
A79: INV1077 | B79: 05-04-2025 | C79: Green Field | D79: haryana | E79: Gurugram | F79: North | G79: Rohit | H79: Farmtrac 45 | I79: 6 | J79: 103288 | K79: 2 | L79: 607333.44 | M79: Partial | N79: Delivered | O79: Valid | P79: Cancelled
A80: INV1078 | B80: 2024/10/23 | C80: Mahadev Motors | D80: Haryana | E80: Gurugram | F80: North | G80: Neha | H80: Farmtrac 60 | I80: 5 | J80: 804507 | K80: 2 | L80: 3942084.3 | M80: Partial | N80: In Transit | O80: Valid | P80: Pending
A81: INV1079 | B81: 2024/04/23 | C81: Shakti Agro | D81: UP | E81: Lucknow | F81: North | G81: Rohit | H81: Kubota MU4501 | J81: 171346 | K81: 12 | M81: Pending | N81: Cancelled | O81: Invalid | P81: Pending
A82: INV1080 | B82: 2024/03/15 | C82: Agri Motors | D82: Maharashtra | E82: Pune | F82: West | G82: PRIYA | H82: Kubota NeoStar | I82: 2 | J82: 854924 | K82: 0 | L82: 1709848 | M82: Partial | N82: Cancelled | O82: Invalid | P82: Pending
A83: INV1081 | B83: 02/14/2024 | C83: Mahadev Motors | D83: Karnataka | E83: Bengaluru | F83: South | G83: Neha | H83: Farmtrac 60 | I83: 5 | J83: 258706 | K83: 12 | L83: 1138306.4 | M83: Paid | N83: Delivered | O83: Invalid | P83: Cancelled
A84: INV1082 | B84: 01/14/2024 | C84: Green Field | D84: Haryana | E84: Gurugram | F84: North | G84: Vikas | H84: Powertrac 439 | I84: 3 | J84: 512291 | K84: 0 | L84: 1536873 | M84: Paid | N84: Delivered | O84: Valid | P84: Cancelled
A85: INV1083 | B85: 11/14/2024 | C85: Kisan Tractors | D85: West Bengal | E85: Kolkata | F85: East | G85: Neha | H85: Farmtrac 45 | I85: 8 | J85: 173310 | K85: 10 | L85: 1247832 | M85: Paid | N85: In Transit | O85: Valid | P85: Pending
A86: INV1084 | B86: 02-04-2024 | C86: Green Field | D86: West Bengal | E86: Kolkata | F86: East | G86: Neha | H86: Kubota MU4501 | I86: 6 | J86: 237351 | K86: 12 | L86: 1253213.3 | M86: Partial | N86: Cancelled | O86: Invalid | P86: Completed
A87: INV1085 | B87: 03/28/2025 | C87: Shakti Agro | D87: UP | E87: Lucknow | F87: North | G87: PRIYA | H87: Farmtrac 45 | I87: 7 | J87: 210905 | K87: 7 | L87: 1372991.6 | M87: Paid | N87: Delivered | O87: Valid | P87: Pending
A88: INV1086 | B88: 2025/03/10 | C88: Kisan Tractors | D88: Haryana | E88: Gurugram | F88: North | G88: Amit | H88: Farmtrac 45 | I88: 8 | J88: 384905 | K88: 5 | L88: 2925278 | M88: Paid | N88: Cancelled | O88: Valid | P88: Completed
A89: INV1087 | B89: 29-05-2024 | C89: Green Field | D89: Karnataka | E89: Bengaluru | F89: South | G89: Priya | H89: Kubota NeoStar | I89: 5 | J89: 632224 | K89: 10 | L89: 2845008 | M89: Partial | N89: Cancelled | O89: Invalid | P89: Cancelled
A90: INV1088 | B90: 27-03-2024 | C90: Green Field | D90: West Bengal | E90: Kolkata | F90: East | G90: Rohit | H90: Kubota NeoStar | I90: 7 | J90: 557033 | K90: 12 | L90: 3431323.3 | M90: Partial | N90: In Transit | O90: Invalid | P90: Completed
A91: INV1089 | B91: 02/10/2024 | C91: Agri Motors | D91: Maharashtra | E91: Pune | F91: West | G91: Rohit | H91: Kubota MU4501 | I91: 3 | J91: 733204 | K91: 5 | L91: 2089631.4 | M91: Partial | N91: In Transit | O91: Valid | P91: Completed
A92: INV1090 | B92: 2024/04/07 | C92: Agri Motors | D92: Maharashtra | E92: Pune | F92: West | G92: Neha | H92: Farmtrac 45 | I92: 4 | J92: 345454 | K92: 2 | L92: 1354179.7 | M92: Pending | N92: Delivered | O92: Valid | P92: Completed
A93: INV1091 | B93: 11/02/2024 | C93: Green Field | D93: Maharashtra | E93: Pune | F93: West | G93: Priya | H93: Kubota NeoStar | I93: 5 | J93: 583573 | K93: 10 | L93: 2626078.5 | M93: Partial | N93: Cancelled | O93: Valid | P93: Pending
... A95: INV1093 | B95: 05/11/2024 | C95: Green Field | D95: UP | E95: Lucknow | F95: North | G95: Vikas | H95: Farmtrac 60 | I95: 6 | J95: 640024 | K95: 12 | L95: 3379326.7 | M95: Pending | N95: Cancelled | O95: Invalid | P95: Completed
A96: INV1094 | B96: 14-11-2024 | C96: Kisan Tractors | D96: Karnataka | E96: Bengaluru | F96: South | G96: Priya | H96: Kubota MU4501 | I96: 8 | J96: 690561 | M96: Partial | N96: Cancelled | O96: Valid | P96: Cancelled
A97: INV1095 | B97: 2025/04/11 | C97: Mahadev Motors | D97: Karnataka | E97: Bengaluru | F97: South | G97: VIKAS | H97: Powertrac 439 | I97: 2 | J97: 689097 | K97: 2 | L97: 1350630.1 | M97: Pending | N97: Delivered | O97: Invalid | P97: Cancelled
A98: INV1096 | B98: 07/17/2024 | C98: Green Field | D98: Maharashtra | E98: Pune | F98: West | G98: Rohit | H98: Kubota MU4501 | I98: 1 | J98: 260229 | K98: 7 | L98: 242012.97 | M98: Pending | N98: Cancelled | O98: Valid | P98: Pending
A99: INV1097 | B99: 2025/04/15 | C99: Agri Motors | D99: Haryana | E99: Gurugram | F99: North | G99: Amit | H99: Farmtrac 45 | I99: 4 | J99: 740417 | K99: 7 | L99: 2754351.2 | M99: Pending | N99: Cancelled | O99: Valid | P99: Completed
A100: INV1098 | B100: 28-02-2025 | C100: Agri Motors | D100: Haryana | E100: Gurugram | F100: North | G100: Neha | H100: Powertrac 439 | I100: 3 | J100: 534614 | K100: 7 | L100: 1491573.1 | M100: Pending | N100: Cancelled | O100: Invalid | P100: Pending
A101: INV1099 | B101: 2025/05/27 | C101: Mahadev Motors | D101: Maharashtra | E101: Pune | F101: West | G101: Priya | H101: Farmtrac 60 | I101: 1 | J101: 318448 | K101: 10 | L101: 286603.2 | M101: Partial | N101: Delivered | O101: Valid | P101: Cancelled
A102: INV1100 | B102: 20-01-2025 | C102: Shakti Agro | D102: West Bengal | E102: Kolkata | F102: East | G102: NEHA | H102: Kubota NeoStar | I102: 8 | J102: 293552 | K102: 7 | L102: 2184026.9 | M102: Partial | N102: Cancelled | O102: Invalid | P102: Pending
A103: INV1101 | B103: 05/20/2024 | C103: Shakti Agro | D103: haryana | E103: Gurugram | F103: North | G103: Vikas | H103: Farmtrac 60 | I103: 5 | J103: 836285 | K103: 2 | L103: 4097796.5 | M103: Paid | N103: Delivered | O103: Valid | P103: Pending
A104: INV1102 | B104: 06/14/2025 | C104: Mahadev Motors | D104: Karnataka | E104: Bengaluru | F104: South | G104: ROHIT | H104: Powertrac 439 | I104: 2 | J104: 418035 | K104: 10 | L104: 752463 | M104: Pending | N104: Cancelled | O104: Valid | P104: Cancelled
A105: INV1103 | B105: 08/07/2024 | C105: Shakti Agro | D105: Uttar Pradesh | E105: Lucknow | F105: North | G105: Amit | H105: Farmtrac 60 | I105: 3 | J105: 366258 | K105: 5 | L105: 1043835.3 | M105: Pending | N105: In Transit | O105: Valid | P105: Cancelled
A106: INV1104 | B106: 2024/12/03 | C106: Mahadev Motors | D106: UP | E106: Lucknow | F106: North | G106: Priya | H106: Kubota NeoStar | I106: 7 | J106: 246449 | K106: 2 | L106: 1690640.1 | M106: Partial | N106: Cancelled | O106: Invalid | P106: Completed
A107: INV1105 | B107: 2024/01/24 | C107: Mahadev Motors | D107: West Bengal | E107: Kolkata | F107: East | G107: VIKAS | H107: Farmtrac 60 | I107: 5 | J107: 617288 | K107: 2 | L107: 3024711.2 | M107: Partial | N107: Cancelled | O107: Valid | P107: Pending
A108: INV1106 | B108: 22-05-2025 | C108: Green Field | D108: Uttar Pradesh | E108: Lucknow | F108: North | G108: Vikas | H108: Farmtrac 45 | I108: 6 | J108: 290458 | K108: 0 | L108: 1742748 | M108: Paid | N108: Delivered | O108: Invalid | P108: Pending
... A118: INV1116 | B118: 2025/05/29 | C118: Mahadev Motors | D118: Uttar Pradesh | E118: Lucknow | F118: North | G118: Amit | H118: Kubota MU4501 | I118: 5 | J118: 465071 | K118: 7 | L118: 2162580.1 | M118: Partial | N118: Cancelled | O118: Invalid | P118: Cancelled
A119: INV1117 | B119: 04/30/2025 | C119: Green Field | D119: UP | E119: Lucknow | F119: North | G119: Vikas | H119: Powertrac 439 | I119: 7 | J119: 627405 | M119: Paid | N119: In Transit | O119: Invalid | P119: Pending
A120: INV1118 | B120: 10/26/2024 | C120: Mahadev Motors | D120: West Bengal | E120: Kolkata | F120: East | G120: Neha | H120: Kubota MU4501 | I120: 1 | J120: 130049 | K120: 10 | L120: 117044.1 | M120: Paid | N120: In Transit | O120: Invalid | P120: Completed
A121: INV1119 | B121: 30-05-2024 | C121: Green Field | D121: West Bengal | E121: Kolkata | F121: East | G121: Neha | H121: Powertrac 439 | I121: 1 | J121: 875064 | K121: 5 | L121: 831310.8 | M121: Partial | N121: In Transit | O121: Valid | P121: Pending
A122: INV1120 | B122: 05/05/2025 | C122: Shakti Agro | D122: Karnataka | E122: Bengaluru | F122: South | G122: Priya | H122: Farmtrac 60 | I122: 8 | J122: 493144 | K122: 10 | L122: 3550636.8 | M122: Paid | N122: Delivered | O122: Invalid | P122: Completed
A123: INV1121 | B123: 14-02-2024 | C123: Green Field | D123: Haryana | E123: Gurugram | F123: North | G123: Amit | H123: Kubota NeoStar | I123: 6 | J123: 693771 | K123: 5 | L123: 3954494.7 | M123: Paid | N123: Cancelled | O123: Valid | P123: Completed
A124: INV1122 | B124: 2024/11/10 | C124: Agri Motors | D124: Karnataka | E124: Bengaluru | F124: South | G124: Amit | H124: Farmtrac 60 | I124: 1 | J124: 535232 | K124: 5 | L124: 508470.4 | M124: Pending | N124: In Transit | O124: Valid | P124: Completed
A125: INV1123 | B125: 15-08-2024 | C125: Mahadev Motors | D125: Haryana | E125: Gurugram | F125: North | G125: Rohit | H125: Farmtrac 45 | I125: 5 | J125: 740850 | K125: 10 | L125: 3333825 | M125: Pending | N125: Cancelled | O125: Invalid | P125: Cancelled
A126: INV1124 | B126: 22-02-2025 | C126: Green Field | D126: Haryana | E126: Gurugram | F126: North | G126: Rohit | H126: Farmtrac 60 | I126: 4 | J126: 620378 | K126: 5 | L126: 2357436.4 | M126: Partial | N126: In Transit | O126: Invalid | P126: Pending
A127: INV1125 | B127: 2025/04/16 | C127: Green Field | D127: maharashtra | E127: Pune | F127: West | G127: Rohit | H127: Farmtrac 60 | I127: 2 | J127: 448402 | K127: 0 | L127: 896804 | M127: Paid | N127: In Transit | O127: Valid | P127: Cancelled
A128: INV1126 | B128: 2024/09/28 | C128: Agri Motors | D128: UP | E128: Lucknow | F128: North | G128: Rohit | H128: Farmtrac 45 | I128: 7 | J128: 204374 | K128: 12 | L128: 1258943.8 | M128: Paid | N128: Delivered | O128: Invalid | P128: Completed
A129: INV1127 | B129: 08/10/2024 | C129: Kisan Tractors | D129: West Bengal | E129: Kolkata | F129: East | G129: ROHIT | H129: Farmtrac 45 | I129: 5 | J129: 288705 | K129: 5 | L129: 1371348.8 | M129: Pending | N129: Delivered | O129: Invalid | P129: Cancelled
A130: INV1128 | B130: 10/31/2024 | C130: Green Field | D130: West Bengal | E130: Kolkata | F130: East | G130: ROHIT | H130: Farmtrac 45 | I130: 3 | J130: 880839 | K130: 2 | L130: 2589666.7 | M130: Paid | N130: Delivered | O130: Invalid | P130: Completed
A131: INV1129 | B131: 2024/08/19 | C131: Agri Motors | D131: UP | E131: Lucknow | F131: North | G131: Priya | H131: Powertrac 439 | I131: 2 | J131: 115561 | K131: 12 | L131: 203387.36 | M131: Pending | N131: Cancelled | O131: Valid | P131: Cancelled
A132: INV1130 | B132: 2024/10/01 | C132: Agri Motors | D132: Haryana | E132: Gurugram | F132: North | G132: Vikas | H132: Kubota NeoStar | I132: 8 | J132: 359954 | K132: 10 | L132: 2591668.8 | M132: Paid | N132: Delivered | O132: Valid | P132: Pending
A133: INV1131 | B133: 04-12-2024 | C133: Green Field | D133: Haryana | E133: Gurugram | F133: North | G133: Neha | H133: Kubota NeoStar | J133: 669206 | K133: 0 | M133: Partial | N133: Cancelled | O133: Valid | P133: Cancelled
A134: INV1132 | B134: 2025/05/24 | C134: Mahadev Motors | D134: karnataka | E134: Bengaluru | F134: South | G134: Vikas | H134: Kubota MU4501 | I134: 4 | J134: 281476 | K134: 0 | L134: 1125904 | M134: Paid | N134: In Transit | O134: Valid | P134: Pending
A135: INV1133 | B135: 2025/06/03 | C135: Agri Motors | D135: UP | E135: Lucknow | F135: North | G135: PRIYA | H135: Kubota MU4501 | J135: 213484 | K135: 0 | M135: Paid | N135: In Transit | O135: Invalid | P135: Cancelled
A136: INV1134 | B136: 03/19/2025 | C136: Green Field | D136: Haryana | E136: Gurugram | F136: North | G136: ROHIT | H136: Kubota NeoStar | I136: 8 | J136: 352004 | K136: 5 | L136: 2675230.4 | M136: Paid | N136: Delivered | O136: Valid | P136: Cancelled
A137: INV1135 | B137: 09-08-2024 | C137: Shakti Agro | D137: Karnataka | E137: Bengaluru | F137: South | G137: ROHIT | H137: Kubota NeoStar | I137: 6 | J137: 148730 | K137: 0 | L137: 892380 | M137: Pending | N137: In Transit | O137: Invalid | P137: Completed
A138: INV1136 | B138: 24-05-2025 | C138: Kisan Tractors | D138: Maharashtra | E138: Pune | F138: West | G138: Vikas | H138: Kubota MU4501 | I138: 6 | J138: 843696 | K138: 10 | L138: 4555958.4 | M138: Paid | N138: Delivered | O138: Invalid | P138: Completed
A139: INV1137 | B139: 06/03/2025 | C139: Mahadev Motors | D139: Uttar Pradesh | E139: Lucknow | F139: North | G139: Vikas | H139: Farmtrac 45 | I139: 1 | J139: 200488 | K139: 5 | L139: 190463.6 | M139: Paid | N139: Delivered | O139: Valid | P139: Cancelled
A140: INV1138 | B140: 03-07-2024 | C140: Kisan Tractors | D140: UP | E140: Lucknow | F140: North | G140: Rohit | H140: Powertrac 439 | I140: 3 | J140: 618174 | K140: 7 | L140: 1724705.5 | M140: Pending | N140: Cancelled | O140: Invalid | P140: Pending
A141: INV1139 | B141: 11-01-2024 | C141: Mahadev Motors | D141: Karnataka | E141: Bengaluru | F141: South | G141: Rohit | H141: Farmtrac 60 | I141: 6 | J141: 253106 | K141: 5 | L141: 1442704.2 | M141: Pending | N141: In Transit | O141: Valid | P141: Cancelled
A142: INV1140 | B142: 2024/09/03 | C142: Agri Motors | D142: Haryana | E142: Gurugram | F142: North | G142: Vikas | H142: Farmtrac 45 | I142: 4 | J142: 579418 | K142: 2 | L142: 2271318.6 | M142: Paid | N142: Cancelled | O142: Valid | P142: Completed
A143: INV1141 | B143: 09-10-2024 | C143: Shakti Agro | D143: Karnataka | E143: Bengaluru | F143: South | G143: Amit | H143: Farmtrac 60 | I143: 2 | J143: 629796 | K143: 10 | L143: 1133632.8 | M143: Partial | N143: Cancelled | O143: Invalid | P143: Cancelled
A144: INV1142 | B144: 01/02/2024 | C144: Agri Motors | D144: west bengal | E144: Kolkata | F144: East | G144: Neha | H144: Powertrac 439 | I144: 7 | J144: 715073 | K144: 12 | L144: 4404849.7 | M144: Pending | N144: Delivered | O144: Invalid | P144: Completed
A145: INV1143 | B145: 06/29/2024 | C145: Agri Motors | D145: West Bengal | E145: Kolkata | F145: East | G145: AMIT | H145: Farmtrac 60 | I145: 1 | J145: 152656 | K145: 7 | L145: 141970.08 | M145: Pending | N145: Cancelled | O145: Valid | P145: Pending
A146: INV1144 | B146: 03/06/2024 | C146: Kisan Tractors | D146: Haryana | E146: Gurugram | F146: North | G146: Rohit | H146: Kubota NeoStar | I146: 7 | J146: 695570 | K146: 10 | L146: 4382091 | M146: Partial | N146: Cancelled | O146: Valid | P146: Pending
A147: INV1145 | B147: 2024/12/09 | C147: Kisan Tractors | D147: Haryana | E147: Gurugram | F147: North | G147: Neha | H147: Farmtrac 60 | I147: 3 | J147: 193437 | K147: 7 | L147: 539689.23 | M147: Pending | N147: In Transit | O147: Valid | P147: Cancelled
... A154: INV1152 | B154: 15-07-2024 | C154: Mahadev Motors | D154: Maharashtra | E154: Pune | F154: West | G154: Amit | H154: Farmtrac 60 | I154: 6 | J154: 818583 | K154: 10 | L154: 4420348.2 | M154: Pending | N154: In Transit | O154: Invalid | P154: Completed
A155: INV1153 | B155: 27-10-2024 | C155: Mahadev Motors | D155: UP | E155: Lucknow | F155: North | G155: Vikas | H155: Powertrac 439 | I155: 8 | J155: 98867 | M155: Partial | N155: Delivered | O155: Invalid | P155: Cancelled
A156: INV1154 | B156: 2025/04/07 | C156: Mahadev Motors | D156: Haryana | E156: Gurugram | F156: North | G156: Amit | H156: Powertrac 439 | I156: 4 | J156: 752299 | K156: 0 | L156: 3009196 | M156: Pending | N156: Cancelled | O156: Invalid | P156: Pending
A157: INV1155 | B157: 23-06-2025 | C157: Kisan Tractors | D157: West Bengal | E157: Kolkata | F157: East | G157: NEHA | H157: Farmtrac 45 | I157: 2 | J157: 177474 | M157: Paid | N157: Cancelled | O157: Invalid | P157: Pending
A158: INV1156 | B158: 17-09-2024 | C158: Mahadev Motors | D158: Haryana | E158: Gurugram | F158: North | G158: ROHIT | H158: Farmtrac 60 | I158: 2 | J158: 175255 | K158: 12 | L158: 308448.8 | M158: Partial | N158: In Transit | O158: Invalid | P158: Cancelled
A159: INV1157 | B159: 07/21/2024 | C159: Green Field | D159: Haryana | E159: Gurugram | F159: North | G159: Rohit | H159: Farmtrac 45 | I159: 6 | J159: 621324 | K159: 5 | L159: 3541546.8 | M159: Paid | N159: In Transit | O159: Invalid | P159: Pending
A160: INV1158 | B160: 2025/04/15 | C160: Kisan Tractors | D160: Karnataka | E160: Bengaluru | F160: South | G160: Amit | H160: Powertrac 439 | I160: 5 | J160: 401357 | K160: 10 | L160: 1806106.5 | M160: Partial | N160: In Transit | O160: Valid | P160: Cancelled
A161: INV1159 | B161: 01/24/2025 | C161: Agri Motors | D161: Karnataka | E161: Bengaluru | F161: South | G161: Vikas | H161: Powertrac 439 | I161: 4 | J161: 177542 | K161: 12 | L161: 624947.84 | M161: Partial | N161: Delivered | O161: Invalid | P161: Completed
A162: INV1160 | B162: 10-05-2024 | C162: Mahadev Motors | D162: UP | E162: Lucknow | F162: North | G162: Priya | H162: Kubota NeoStar | I162: 6 | J162: 682346 | K162: 7 | L162: 3807490.7 | M162: Paid | N162: Delivered | O162: Invalid | P162: Completed
A163: INV1161 | B163: 2024/09/16 | C163: Kisan Tractors | D163: Maharashtra | E163: Pune | F163: West | G163: ROHIT | H163: Farmtrac 60 | I163: 2 | J163: 685783 | K163: 10 | L163: 1234409.4 | M163: Paid | N163: In Transit | O163: Valid | P163: Completed
...

Sheet Master Sheet
B2: Discount (%) Allotment Table
B3: Tractor Quantity Purchased | C3: Discount Allotment | E3: Product Category Assignment
B4: 0 | C4: 0 | E4: Product Model | F4: Product Category
B5: 1 | C5: 3 | E5: Farmtrac 60 | F5: Farmtrac
B6: 2 | C6: 5 | E6: Kubota Mu4501 | F6: Kubota
B7: 3 | C7: 6 | E7: Farmtrac 45 | F7: Farmtrac
B8: 4 | C8: 6 | E8: Powertrac 439 | F8: Powertrac
B9: 5 | C9: 7 | E9: Kubota Neostar | F9: Kubota
B10: 6 | C10: 8
B11: 7 | C11: 9
B12: 8 | C12: 9
B16: Average of Discount % | E16: Region Table
B17: 6.482567 | E17: City Name | F17: Region
E18: Lucknow | F18: North
E19: Bengaluru | F19: South
E20: Pune | F20: West
E21: Gurugram | F21: North
E22: Kolkata | F22: East

Sheet Cleaned Data
A1: Invoice ID | B1: Order Date | C1: Sales Executive | D1: Dealer Name | E1: State | F1: Dealer Master Key | G1: City | H1: Region | I1: Tractor Model | J1: Brand Name | K1: Quantity | L1: Unit Price | M1: Discount % | N1: Gross Amount | O1: Gross Amount (Cr) | P1: Net Sales Amount | Q1: Net Sales (Cr) | R1: Payment Status | S1: Delivery Status | T1: GST Status | U1: Order Status
A2: INV1000 | B2: 45405 | C2: Neha | D2: Shakti | E2: Uttar Pradesh | F2: Shakti Agro Uttar Pradesh | G2: Lucknow | H2: =VLOOKUP(Table1[[#This Row],[City]],Table6[#All],2,FALSE) -> North | I2: Farmtrac 60 | J2: =_xlfn.XLOOKUP(Table1[[#This Row],[Tractor Model]],Table7[Product Model],Table7[Product Category],"Not Available",0) -> Farmtrac | K2: 1 | L2: 810386 | M2: =INDEX('Master Sheet'!$C$4:$C$12,MATCH(Table1[[#This Row],[Quantity]],'Master Sheet'!$B$4:$B$12,0)) -> 3 | N2: =Table1[[#This Row],[Quantity]]*Table1[[#This Row],[Unit Price]] -> 810386 | O2: 0.0810386 | P2: =Table1[[#This Row],[Gross Amount]]*(1-(Table1[[#This Row],[Discount %]]/100)) -> 786074.42 | Q2: =(Table1[[#This Row],[Gross Amount]]*(1-(Table1[[#This Row],[Discount %]]/100)))/10000000 -> 0.078607442 | R2: Partial | S2: {=IFERROR(_xlfn.IFS(Table1[[#This Row],[Payment Status]]="Partial","In Transit",Table1[[#This Row],[Payment Status]]="Paid","Delivered",Table1[[#This Row],[Payment Status]]="Pending","Pending"),"Invalid Input")} -> In Transit | T2: Invalid | U2: {=IFERROR(_xlfn.IFS(Table1[[#This Row],[Payment Status]]="Partial","In Transit",Table1[[#This Row],[Payment Status]]="Paid","Completed",Table1[[#This Row],[Payment Status]]="Pending","Pending"),"Invalid Input")} -> In Transit
A3: INV1001 | B3: 45326 | C3: Priya | D3: Shakti | E3: Karnataka | F3: Shakti Agro Karnataka | G3: Bengaluru | H3: =VLOOKUP(Table1[[#This Row],[City]],Table6[#All],2,FALSE) -> South | I3: Kubota Mu4501 | J3: =_xlfn.XLOOKUP(Table1[[#This Row],[Tractor Model]],Table7[Product Model],Table7[Product Category],"Not Available",0) -> Kubota | K3: 6 | L3: 421642 | M3: =INDEX('Master Sheet'!$C$4:$C$12,MATCH(Table1[[#This Row],[Quantity]],'Master Sheet'!$B$4:$B$12,0)) -> 8 | N3: =Table1[[#This Row],[Quantity]]*Table1[[#This Row],[Unit Price]] -> 2529852 | O3: 0.2529852 | P3: =Table1[[#This Row],[Gross Amount]]*(1-(Table1[[#This Row],[Discount %]]/100)) -> 2327463.8 | Q3: =(Table1[[#This Row],[Gross Amount]]*(1-(Table1[[#This Row],[Discount %]]/100)))/10000000 -> 0.23274638 | R3: Partial | S3: {=IFERROR(_xlfn.IFS(Table1[[#This Row],[Payment Status]]="Partial","In Transit",Table1[[#This Row],[Payment Status]]="Paid","Delivered",Table1[[#This Row],[Payment Status]]="Pending","Pending"),"Invalid Input")} -> In Transit | T3: Invalid | U3: {=IFERROR(_xlfn.IFS(Table1[[#This Row],[Payment Status]]="Partial","In Transit",Table1[[#This Row],[Payment Status]]="Paid","Completed",Table1[[#This Row],[Payment Status]]="Pending","Pending"),"Invalid Input")} -> In Transit
A4: INV1002 | B4: 45657 | C4: Amit | D4: Green Field | E4: Maharashtra | F4: Green Field Maharashtra | G4: Pune | H4: =VLOOKUP(Table1[[#This Row],[City]],Table6[#All],2,FALSE) -> West | I4: Kubota Mu4501 | J4: =_xlfn.XLOOKUP(Table1[[#This Row],[Tractor Model]],Table7[Product Model],Table7[Product Category],"Not Available",0) -> Kubota | K4: 7 | L4: 58962 | M4: =INDEX('Master Sheet'!$C$4:$C$12,MATCH(Table1[[#This Row],[Quantity]],'Master Sheet'!$B$4:$B$12,0)) -> 9 | N4: =Table1[[#This Row],[Quantity]]*Table1[[#This Row],[Unit Price]] -> 412734 | O4: 0.0412734 | P4: =Table1[[#This Row],[Gross Amount]]*(1-(Table1[[#This Row],[Discount %]]/100)) -> 375587.94 | Q4: =(Table1[[#This Row],[Gross Amount]]*(1-(Table1[[#This Row],[Discount %]]/100)))/10000000 -> 0.037558794 | R4: Pending | S4: {=IFERROR(_xlfn.IFS(Table1[[#This Row],[Payment Status]]="Partial","In Transit",Table1[[#This Row],[Payment Status]]="Paid","Delivered",Table1[[#This Row],[Payment Status]]="Pending","Pending"),"Invalid Input")} -> Pending | T4: Invalid | U4: {=IFERROR(_xlfn.IFS(Table1[[#This Row],[Payment Status]]="Partial","In Transit",Table1[[#This Row],[Payment Status]]="Paid","Completed",Table1[[#This Row],[Payment Status]]="Pending","Pending"),"Invalid Input")} -> Pending
A5: INV1003 | B5: 45550 | C5: Priya | D5: Green Field | E5: Haryana | F5: Green Field Haryana | G5: Gurugram | H5: =VLOOKUP(Table1[[#This Row],[City]],Table6[#All],2,FALSE) -> North | I5: Kubota Mu4501 | J5: =_xlfn.XLOOKUP(Table1[[#This Row],[Tractor Model]],Table7[Product Model],Table7[Product Category],"Not Available",0) -> Kubota | K5: 7 | L5: 640018 | M5: =INDEX('Master Sheet'!$C$4:$C$12,MATCH(Table1[[#This Row],[Quantity]],'Master Sheet'!$B$4:$B$12,0)) -> 9 | N5: =Table1[[#This Row],[Quantity]]*Table1[[#This Row],[Unit Price]] -> 4480126 | O5: 0.4480126 | P5: =Table1[[#This Row],[Gross Amount]]*(1-(Table1[[#This Row],[Discount %]]/100)) -> 4076914.7 | Q5: =(Table1[[#This Row],[Gross Amount]]*(1-(Table1[[#This Row],[Discount %]]/100)))/10000000 -> 0.40769147 | R5: Partial | S5: {=IFERROR(_xlfn.IFS(Table1[[#This Row],[Payment Status]]="Partial","In Transit",Table1[[#This Row],[Payment Status]]="Paid","Delivered",Table1[[#This Row],[Payment Status]]="Pending","Pending"),"Invalid Input")} -> In Transit | T5: Invalid | U5: {=IFERROR(_xlfn.IFS(Table1[[#This Row],[Payment Status]]="Partial","In Transit",Table1[[#This Row],[Payment Status]]="Paid","Completed",Table1[[#This Row],[Payment Status]]="Pending","Pending"),"Invalid Input")} -> In Transit
A6: INV1004 | B6: 45805 | C6: Neha | D6: Shakti | E6: Haryana | F6: Shakti Agro Haryana | G6: Gurugram | H6: =VLOOKUP(Table1[[#This Row],[City]],Table6[#All],2,FALSE) -> North | I6: Farmtrac 45 | J6: =_xlfn.XLOOKUP(Table1[[#This Row],[Tractor Model]],Table7[Product Model],Table7[Product Category],"Not Available",0) -> Farmtrac | K6: 2 | L6: 736528 | M6: =INDEX('Master Sheet'!$C$4:$C$12,MATCH(Table1[[#This Row],[Quantity]],'Master Sheet'!$B$4:$B$12,0)) -> 5 | N6: =Table1[[#This Row],[Quantity]]*Table1[[#This Row],[Unit Price]] -> 1473056 | O6: 0.1473056 | P6: =Table1[[#This Row],[Gross Amount]]*(1-(Table1[[#This Row],[Discount %]]/100)) -> 1399403.2 | Q6: =(Table1[[#This Row],[Gross Amount]]*(1-(Table1[[#This Row],[Discount %]]/100)))/10000000 -> 0.13994032 | R6: Paid | S6: {=IFERROR(_xlfn.IFS(Table1[[#This Row],[Payment Status]]="Partial","In Transit",Table1[[#This Row],[Payment Status]]="Paid","Delivered",Table1[[#This Row],[Payment Status]]="Pending","Pending"),"Invalid Input")} -> Delivered | T6: Valid | U6: {=IFERROR(_xlfn.IFS(Table1[[#This Row],[Payment Status]]="Partial","In Transit",Table1[[#This Row],[Payment Status]]="Paid","Completed",Table1[[#This Row],[Payment Status]]="Pending","Pending"),"Invalid Input")} -> Completed
A7: INV1005 | B7: 45743 | C7: Amit | D7: Green Field | E7: Uttar Pradesh | F7: Green Field Uttar Pradesh | G7: Lucknow | H7: =VLOOKUP(Table1[[#This Row],[City]],Table6[#All],2,FALSE) -> North | I7: Powertrac 439 | J7: =_xlfn.XLOOKUP(Table1[[#This Row],[Tractor Model]],Table7[Product Model],Table7[Product Category],"Not Available",0) -> Powertrac | K7: 3 | L7: 446618 | M7: =INDEX('Master Sheet'!$C$4:$C$12,MATCH(Table1[[#This Row],[Quantity]],'Master Sheet'!$B$4:$B$12,0)) -> 6 | N7: =Table1[[#This Row],[Quantity]]*Table1[[#This Row],[Unit Price]] -> 1339854 | O7: 0.1339854 | P7: =Table1[[#This Row],[Gross Amount]]*(1-(Table1[[#This Row],[Discount %]]/100)) -> 1259462.8 | Q7: =(Table1[[#This Row],[Gross Amount]]*(1-(Table1[[#This Row],[Discount %]]/100)))/10000000 -> 0.12594628 | R7: Pending | S7: {=IFERROR(_xlfn.IFS(Table1[[#This Row],[Payment Status]]="Partial","In Transit",Table1[[#This Row],[Payment Status]]="Paid","Delivered",Table1[[#This Row],[Payment Status]]="Pending","Pending"),"Invalid Input")} -> Pending | T7: Valid | U7: {=IFERROR(_xlfn.IFS(Table1[[#This Row],[Payment Status]]="Partial","In Transit",Table1[[#This Row],[Payment Status]]="Paid","Completed",Table1[[#This Row],[Payment Status]]="Pending","Pending"),"Invalid Input")} -> Pending
A8: INV1006 | B8: 45574 | C8: Vikas | D8: Green Field | E8: Maharashtra | F8: Green Field Maharashtra | G8: Pune | H8: =VLOOKUP(Table1[[#This Row],[City]],Table6[#All],2,FALSE) -> West | I8: Powertrac 439 | J8: =_xlfn.XLOOKUP(Table1[[#This Row],[Tractor Model]],Table7[Product Model],Table7[Product Category],"Not Available",0) -> Powertrac | K8: 4 | L8: 636846 | M8: =INDEX('Master Sheet'!$C$4:$C$12,MATCH(Table1[[#This Row],[Quantity]],'Master Sheet'!$B$4:$B$12,0)) -> 6 | N8: =Table1[[#This Row],[Quantity]]*Table1[[#This Row],[Unit Price]] -> 2547384 | O8: 0.2547384 | P8: =Table1[[#This Row],[Gross Amount]]*(1-(Table1[[#This Row],[Discount %]]/100)) -> 2394541 | Q8: =(Table1[[#This Row],[Gross Amount]]*(1-(Table1[[#This Row],[Discount %]]/100)))/10000000 -> 0.2394541 | R8: Partial | S8: {=IFERROR(_xlfn.IFS(Table1[[#This Row],[Payment Status]]="Partial","In Transit",Table1[[#This Row],[Payment Status]]="Paid","Delivered",Table1[[#This Row],[Payment Status]]="Pending","Pending"),"Invalid Input")} -> In Transit | T8: Invalid | U8: {=IFERROR(_xlfn.IFS(Table1[[#This Row],[Payment Status]]="Partial","In Transit",Table1[[#This Row],[Payment Status]]="Paid","Completed",Table1[[#This Row],[Payment Status]]="Pending","Pending"),"Invalid Input")} -> In Transit
A9: INV1007 | B9: 45613 | C9: Neha | D9: Kisan | E9: West Bengal | F9: Kisan Tractors West Bengal | G9: Kolkata | H9: =VLOOKUP(Table1[[#This Row],[City]],Table6[#All],2,FALSE) -> East | I9: Farmtrac 45 | J9: =_xlfn.XLOOKUP(Table1[[#This Row],[Tractor Model]],Table7[Product Model],Table7[Product Category],"Not Available",0) -> Farmtrac | K9: 4 | L9: 87171 | M9: =INDEX('Master Sheet'!$C$4:$C$12,MATCH(Table1[[#This Row],[Quantity]],'Master Sheet'!$B$4:$B$12,0)) -> 6 | N9: =Table1[[#This Row],[Quantity]]*Table1[[#This Row],[Unit Price]] -> 348684 | O9: 0.0348684 | P9: =Table1[[#This Row],[Gross Amount]]*(1-(Table1[[#This Row],[Discount %]]/100)) -> 327762.96 | Q9: =(Table1[[#This Row],[Gross Amount]]*(1-(Table1[[#This Row],[Discount %]]/100)))/10000000 -> 0.032776296 | R9: Pending | S9: {=IFERROR(_xlfn.IFS(Table1[[#This Row],[Payment Status]]="Partial","In Transit",Table1[[#This Row],[Payment Status]]="Paid","Delivered",Table1[[#This Row],[Payment Status]]="Pending","Pending"),"Invalid Input")} -> Pending | T9: Valid | U9: {=IFERROR(_xlfn.IFS(Table1[[#This Row],[Payment Status]]="Partial","In Transit",Table1[[#This Row],[Payment Status]]="Paid","Completed",Table1[[#This Row],[Payment Status]]="Pending","Pending"),"Invalid Input")} -> Pending
A10: INV1008 | B10: 45605 | C10: Rohit | D10: Kisan | E10: Haryana | F10: Kisan Tractors Haryana | G10: Gurugram | H10: =VLOOKUP(Table1[[#This Row],[City]],Table6[#All],2,FALSE) -> North | I10: Kubota Mu4501 | J10: =_xlfn.XLOOKUP(Table1[[#This Row],[Tractor Model]],Table7[Product Model],Table7[Product Category],"Not Available",0) -> Kubota | K10: 6 | L10: 435799 | M10: =INDEX('Master Sheet'!$C$4:$C$12,MATCH(Table1[[#This Row],[Quantity]],'Master Sheet'!$B$4:$B$12,0)) -> 8 | N10: =Table1[[#This Row],[Quantity]]*Table1[[#This Row],[Unit Price]] -> 2614794 | O10: 0.2614794 | P10: =Table1[[#This Row],[Gross Amount]]*(1-(Table1[[#This Row],[Discount %]]/100)) -> 2405610.5 | Q10: =(Table1[[#This Row],[Gross Amount]]*(1-(Table1[[#This Row],[Discount %]]/100)))/10000000 -> 0.24056105 | R10: Paid | S10: {=IFERROR(_xlfn.IFS(Table1[[#This Row],[Payment Status]]="Partial","In Transit",Table1[[#This Row],[Payment Status]]="Paid","Delivered",Table1[[#This Row],[Payment Status]]="Pending","Pending"),"Invalid Input")} -> Delivered | T10: Valid | U10: {=IFERROR(_xlfn.IFS(Table1[[#This Row],[Payment Status]]="Partial","In Transit",Table1[[#This Row],[Payment Status]]="Paid","Completed",Table1[[#This Row],[Payment Status]]="Pending","Pending"),"Invalid Input")} -> Completed
A11: INV1009 | B11: 45619 | C11: Priya | D11: Mahadev | E11: Karnataka | F11: Mahadev Motors Karnataka | G11: Bengaluru | H11: =VLOOKUP(Table1[[#This Row],[City]],Table6[#All],2,FALSE) -> South | I11: Farmtrac 45 | J11: =_xlfn.XLOOKUP(Table1[[#This Row],[Tractor Model]],Table7[Product Model],Table7[Product Category],"Not Available",0) -> Farmtrac | K11: 3 | L11: 91771 | M11: =INDEX('Master Sheet'!$C$4:$C$12,MATCH(Table1[[#This Row],[Quantity]],'Master Sheet'!$B$4:$B$12,0)) -> 6 | N11: =Table1[[#This Row],[Quantity]]*Table1[[#This Row],[Unit Price]] -> 275313 | O11: 0.0275313 | P11: =Table1[[#This Row],[Gross Amount]]*(1-(Table1[[#This Row],[Discount %]]/100)) -> 258794.22 | Q11: =(Table1[[#This Row],[Gross Amount]]*(1-(Table1[[#This Row],[Discount %]]/100)))/10000000 -> 0.025879422 | R11: Paid | S11: {=IFERROR(_xlfn.IFS(Table1[[#This Row],[Payment Status]]="Partial","In Transit",Table1[[#This Row],[Payment Status]]="Paid","Delivered",Table1[[#This Row],[Payment Status]]="Pending","Pending"),"Invalid Input")} -> Delivered | T11: Invalid | U11: {=IFERROR(_xlfn.IFS(Table1[[#This Row],[Payment Status]]="Partial","In Transit",Table1[[#This Row],[Payment Status]]="Paid","Completed",Table1[[#This Row],[Payment Status]]="Pending","Pending"),"Invalid Input")} -> Completed
A12: INV1010 | B12: 45329 | C12: Neha | D12: Mahadev | E12: Uttar Pradesh | F12: Mahadev Motors Uttar Pradesh | G12: Lucknow | H12: =VLOOKUP(Table1[[#This Row],[City]],Table6[#All],2,FALSE) -> North | I12: Powertrac 439 | J12: =_xlfn.XLOOKUP(Table1[[#This Row],[Tractor Model]],Table7[Product Model],Table7[Product Category],"Not Available",0) -> Powertrac | K12: 1 | L12: 366788 | M12: =INDEX('Master Sheet'!$C$4:$C$12,MATCH(Table1[[#This Row],[Quantity]],'Master Sheet'!$B$4:$B$12,0)) -> 3 | N12: =Table1[[#This Row],[Quantity]]*Table1[[#This Row],[Unit Price]] -> 366788 | O12: 0.0366788 | P12: =Table1[[#This Row],[Gross Amount]]*(1-(Table1[[#This Row],[Discount %]]/100)) -> 355784.36 | Q12: =(Table1[[#This Row],[Gross Amount]]*(1-(Table1[[#This Row],[Discount %]]/100)))/10000000 -> 0.035578436 | R12: Partial | S12: {=IFERROR(_xlfn.IFS(Table1[[#This Row],[Payment Status]]="Partial","In Transit",Table1[[#This Row],[Payment Status]]="Paid","Delivered",Table1[[#This Row],[Payment Status]]="Pending","Pending"),"Invalid Input")} -> In Transit | T12: Valid | U12: {=IFERROR(_xlfn.IFS(Table1[[#This Row],[Payment Status]]="Partial","In Transit",Table1[[#This Row],[Payment Status]]="Paid","Completed",Table1[[#This Row],[Payment Status]]="Pending","Pending"),"Invalid Input")} -> In Transit
A13: INV1011 | B13: 45673 | C13: Rohit | D13: Kisan | E13: West Bengal | F13: Kisan Tractors West Bengal | G13: Kolkata | H13: =VLOOKUP(Table1[[#This Row],[City]],Table6[#All],2,FALSE) -> East | I13: Powertrac 439 | J13: =_xlfn.XLOOKUP(Table1[[#This Row],[Tractor Model]],Table7[Product Model],Table7[Product Category],"Not Available",0) -> Powertrac | K13: 8 | L13: 745852 | M13: =INDEX('Master Sheet'!$C$4:$C$12,MATCH(Table1[[#This Row],[Quantity]],'Master Sheet'!$B$4:$B$12,0)) -> 9 | N13: =Table1[[#This Row],[Quantity]]*Table1[[#This Row],[Unit Price]] -> 5966816 | O13: 0.5966816 | P13: =Table1[[#This Row],[Gross Amount]]*(1-(Table1[[#This Row],[Discount %]]/100)) -> 5429802.6 | Q13: =(Table1[[#This Row],[Gross Amount]]*(1-(Table1[[#This Row],[Discount %]]/100)))/10000000 -> 0.54298026 | R13: Paid | S13: {=IFERROR(_xlfn.IFS(Table1[[#This Row],[Payment Status]]="Partial","In Transit",Table1[[#This Row],[Payment Status]]="Paid","Delivered",Table1[[#This Row],[Payment Status]]="Pending","Pending"),"Invalid Input")} -> Delivered | T13: Invalid | U13: {=IFERROR(_xlfn.IFS(Table1[[#This Row],[Payment Status]]="Partial","In Transit",Table1[[#This Row],[Payment Status]]="Paid","Completed",Table1[[#This Row],[Payment Status]]="Pending","Pending"),"Invalid Input")} -> Completed
... A1980: INV2999 | B1980: 45506 | C1980: Vikas | D1980: Kisan | E1980: West Bengal | F1980: Kisan Tractors West Bengal | G1980: Kolkata | H1980: =VLOOKUP(Table1[[#This Row],[City]],Table6[#All],2,FALSE) -> East | I1980: Powertrac 439 | J1980: =_xlfn.XLOOKUP(Table1[[#This Row],[Tractor Model]],Table7[Product Model],Table7[Product Category],"Not Available",0) -> Powertrac | K1980: 4 | L1980: 223670 | M1980: =INDEX('Master Sheet'!$C$4:$C$12,MATCH(Table1[[#This Row],[Quantity]],'Master Sheet'!$B$4:$B$12,0)) -> 6 | N1980: =Table1[[#This Row],[Quantity]]*Table1[[#This Row],[Unit Price]] -> 894680 | O1980: 0.089468 | P1980: =Table1[[#This Row],[Gross Amount]]*(1-(Table1[[#This Row],[Discount %]]/100)) -> 840999.2 | Q1980: =(Table1[[#This Row],[Gross Amount]]*(1-(Table1[[#This Row],[Discount %]]/100)))/10000000 -> 0.08409992 | R1980: Paid | S1980: {=IFERROR(_xlfn.IFS(Table1[[#This Row],[Payment Status]]="Partial","In Transit",Table1[[#This Row],[Payment Status]]="Paid","Delivered",Table1[[#This Row],[Payment Status]]="Pending","Pending"),"Invalid Input")} -> Delivered | T1980: Invalid | U1980: {=IFERROR(_xlfn.IFS(Table1[[#This Row],[Payment Status]]="Partial","In Transit",Table1[[#This Row],[Payment Status]]="Paid","Completed",Table1[[#This Row],[Payment Status]]="Pending","Pending"),"Invalid Input")} -> Completed

Sheet Executive Sales Report
B2: Sum of Net Sales Amount | C2: Region | J2: Sum of Net Sales (Cr) | K2: Column Labels
B3: City | C3: East | D3: North | E3: South | F3: West | G3: Grand Total | J3: Row Labels | K3: East | L3: North | M3: South | N3: West | O3: Grand Total
B4: Bengaluru | E4: 6.7072791e+08 | G4: 6.7072791e+08 | J4: Bengaluru | M4: 67.072791 | O4: 67.072791
B5: Gurugram | D5: 7.7345772e+08 | G5: 7.7345772e+08 | J5: Gurugram | L5: 77.345772 | O5: 77.345772
B6: Kolkata | C6: 7.9348841e+08 | G6: 7.9348841e+08 | J6: Kolkata | K6: 79.348841 | O6: 79.348841
B7: Lucknow | D7: 7.8534235e+08 | G7: 7.8534235e+08 | J7: Lucknow | L7: 78.534235 | O7: 78.534235
B8: Pune | F8: 7.5501049e+08 | G8: 7.5501049e+08 | J8: Pune | N8: 75.501049 | O8: 75.501049
B9: Grand Total | C9: 7.9348841e+08 | D9: 1.5588001e+09 | E9: 6.7072791e+08 | F9: 7.5501049e+08 | G9: 3.7780269e+09 | J9: Grand Total | K9: 79.348841 | L9: 155.88001 | M9: 67.072791 | N9: 75.501049 | O9: 377.80269
B12: Orders Quantity By Dealers | C12: Quantity Sales By State
B13: Dealers Name | C13: Haryana | D13: Karnataka | E13: Maharashtra | F13: Uttar Pradesh | G13: West Bengal | H13: Grand Total
B14: Green Field | C14: 392 | D14: 290 | E14: 329 | F14: 390 | G14: 396 | H14: 1797
B15: Shakti | C15: 287 | D15: 329 | E15: 382 | F15: 353 | G15: 382 | H15: 1733
B16: Kisan | C16: 328 | D16: 348 | E16: 344 | F16: 391 | G16: 359 | H16: 1770
B17: Mahadev | C17: 343 | D17: 318 | E17: 334 | F17: 367 | G17: 366 | H17: 1728
B18: Agri | C18: 403 | D18: 302 | E18: 334 | F18: 308 | G18: 344 | H18: 1691
B19: Grand Total | C19: 1753 | D19: 1587 | E19: 1723 | F19: 1809 | G19: 1847 | H19: 8719
B22: Sales By Months | C22: Years
B23: Months | C23: 2024 | D23: 2025 | E23: Grand Total
B24: Jan | C24: 2.2843204e+08 | D24: 1.6866153e+08 | E24: 3.9709357e+08
B25: Feb | C25: 2.2387996e+08 | D25: 1.9479548e+08 | E25: 4.1867543e+08
B26: Mar | C26: 2.4408945e+08 | D26: 1.7687618e+08 | E26: 4.2096563e+08
B27: Apr | C27: 1.711359e+08 | D27: 2.0261889e+08 | E27: 3.7375479e+08
B28: May | C28: 1.9725482e+08 | D28: 2.0371792e+08 | E28: 4.0097274e+08
B29: Jun | C29: 1.885241e+08 | D29: 1.3760376e+08 | E29: 3.2612787e+08
B30: Grand Total | C30: 1.2533163e+09 | D30: 1.0842738e+09 | E30: 2.33759e+09
B33: Region | C33: Sum of Gross Amount | D33: Sum of Net Sales Amount | F33: Row Labels | G33: Sum of Gross Amount (Cr) | H33: Sum of Net Sales (Cr)
B34: East | C34: 859612610 | D34: 7.9348841e+08 | F34: East | G34: 85.961261 | H34: 79.348841
B35: North | C35: 1684832443 | D35: 1.5588001e+09 | F35: North | G35: 168.48324 | H35: 155.88001
B36: South | C36: 725339193 | D36: 6.7072791e+08 | F36: South | G36: 72.533919 | H36: 67.072791
B37: West | C37: 816612672 | D37: 7.5501049e+08 | F37: West | G37: 81.661267 | H37: 75.501049
B38: Grand Total | C38: 4086396918 | D38: 3.7780269e+09 | F38: Grand Total | G38: 408.63969 | H38: 377.80269
B41: Sum of Net Sales (Cr) | C41: Months
B42: Region | C42: East | D42: North | E42: South | F42: West | G42: Grand Total
B43: Jan | C43: 8.9398105 | D43: 15.025944 | E43: 6.9725885 | F43: 8.7710139 | G43: 39.709357
B44: Feb | C44: 8.7207542 | D44: 15.469876 | E44: 8.1903596 | F44: 9.4865531 | G44: 41.867543
B45: Mar | C45: 7.245783 | D45: 18.461116 | E45: 8.3464439 | F45: 8.0432205 | G45: 42.096563
B46: Apr | C46: 7.2304471 | D46: 16.38942 | E46: 5.7633444 | F46: 7.9922675 | G46: 37.375479
B47: May | C47: 7.137434 | D47: 17.436992 | E47: 7.9369194 | F47: 7.5859285 | G47: 40.097274
B48: Jun | C48: 5.5719658 | D48: 15.041575 | E48: 7.1944191 | F48: 4.8048267 | G48: 32.612787
B49: Jul | C49: 5.9330865 | D49: 8.6205536 | E49: 2.9898679 | F49: 4.9791118 | G49: 22.52262
B50: Aug | C50: 5.2835315 | D50: 11.120147 | E50: 3.0620912 | F50: 4.1168296 | G50: 23.582599
B51: Sep | C51: 6.1884797 | D51: 10.128025 | E51: 3.5681976 | F51: 3.6569687 | G51: 23.541671
B52: Oct | C52: 4.7132 | D52: 8.9135765 | E52: 4.9762939 | F52: 4.152184 | G52: 22.755254
B53: Nov | C53: 5.599989 | D53: 8.963158 | E53: 5.4105615 | F53: 5.3045919 | G53: 25.2783
B54: Dec | C54: 6.7843599 | D54: 10.309623 | E54: 2.6617044 | F54: 6.6075525 | G54: 26.36324
B55: Grand Total | C55: 79.348841 | D55: 155.88001 | E55: 67.072791 | F55: 75.501049 | G55: 377.80269
C58: Column Labels
C59: INV1000 | D59: INV1001 | E59: INV1002 | F59: INV1003 | G59: INV1004 | H59: INV1005 | I59: INV1006 | J59: INV1007 | K59: INV1008 | L59: INV1009 | M59: INV1010 | N59: INV1011 | O59: INV1012 | P59: INV1013 | Q59: INV1014 | R59: INV1015 | S59: INV1016 | T59: INV1017 | U59: INV1018 | V59: INV1019 | W59: INV1020 | X59: INV1021 | Y59: INV1022 | Z59: INV1023 | AA59: INV1024 | AB59: INV1025 | AC59: INV1026 | AD59: INV1027 | AE59: INV1028 | AF59: INV1029 | AG59: INV1030 | AH59: INV1031 | AI59: INV1032 | AJ59: INV1033 | AK59: INV1034 | AL59: INV1035 | AM59: INV1036 | AN59: INV1037 | AO59: INV1038 | AP59: INV1039 | AQ59: INV1040 | AR59: INV1042 | AS59: INV1043 | AT59: INV1044 | AU59: INV1045 | AV59: INV1046 | AW59: INV1047 | AX59: INV1048 | AY59: INV1049 | AZ59: INV1050 | BA59: INV1051 | BB59: INV1052 | BC59: INV1053 | BD59: INV1054 | BE59: INV1055 | BF59: INV1056 | BG59: INV1057 | BH59: INV1058 | BI59: INV1059 | BJ59: INV1060 | BK59: INV1061 | BL59: INV1062 | BM59: INV1063 | BN59: INV1064 | BO59: INV1065 | BP59: INV1066 | BQ59: INV1067 | BR59: INV1068 | BS59: INV1069 | BT59: INV1070 | BU59: INV1071 | BV59: INV1072 | BW59: INV1073 | BX59: INV1074 | BY59: INV1075 | BZ59: INV1076 | CA59: INV1077 | CB59: INV1078 | CC59: INV1079 | CD59: INV1080 | CE59: INV1081 | CF59: INV1082 | CG59: INV1083 | CH59: INV1084 | CI59: INV1085 | CJ59: INV1086 | CK59: INV1087 | CL59: INV1088 | CM59: INV1089 | CN59: INV1090 | CO59: INV1091 | CP59: INV1092 | CQ59: INV1093 | CR59: INV1094 | CS59: INV1095 | CT59: INV1096 | CU59: INV1097 | CV59: INV1098 | CW59: INV1099 | CX59: INV1100 | CY59: INV1101 | CZ59: INV1102 | DA59: INV1103 | DB59: INV1104 | DC59: INV1105 | DD59: INV1106 | DE59: INV1107 | DF59: INV1108 | DG59: INV1109 | DH59: INV1110 | DI59: INV1111 | DJ59: INV1112 | DK59: INV1113 | DL59: INV1114 | DM59: INV1115 | DN59: INV1116 | DO59: INV1117 | DP59: INV1118 | DQ59: INV1119 | DR59: INV1120 | DS59: INV1121 | DT59: INV1122 | DU59: INV1123 | DV59: INV1124 | DW59: INV1125 | DX59: INV1126 | DY59: INV1127 | DZ59: INV1128 | EA59: INV1129 | EB59: INV1130 | EC59: INV1131 | ED59: INV1132 | EE59: INV1133 | EF59: INV1134 | EG59: INV1135 | EH59: INV1136 | EI59: INV1137 | EJ59: INV1138 | EK59: INV1139 | EL59: INV1140 | EM59: INV1141 | EN59: INV1142 | EO59: INV1143 | EP59: INV1144 | EQ59: INV1145 | ER59: INV1146 | ES59: INV1147 | ET59: INV1148 | EU59: INV1149 | EV59: INV1150 | EW59: INV1151 | EX59: INV1152 | EY59: INV1153 | EZ59: INV1154 | FA59: INV1155 | FB59: INV1156 | FC59: INV1157 | FD59: INV1158 | FE59: INV1159 | FF59: INV1160 | FG59: INV1161 | FH59: INV1162 | FI59: INV1163 | FJ59: INV1164 | FK59: INV1165 | FL59: INV1166 | FM59: INV1167 | FN59: INV1168 | FO59: INV1169 | FP59: INV1170 | FQ59: INV1171 | FR59: INV1172 | FS59: INV1173 | FT59: INV1174 | FU59: INV1175 | FV59: INV1176 | FW59: INV1177 | FX59: INV1178 | FY59: INV1179 | FZ59: INV1180 | GA59: INV1181 | GB59: INV1182 | GC59: INV1183 | GD59: INV1184 | GE59: INV1185 | GF59: INV1186 | GG59: INV1187 | GH59: INV1188 | GI59: INV1189 | GJ59: INV1190 | GK59: INV1191 | GL59: INV1192 | GM59: INV1193 | GN59: INV1194 | GO59: INV1195 | GP59: INV1196 | GQ59: INV1197 | GR59: INV1198 | GS59: INV1199 | GT59: INV1200 | GU59: INV1201 | GV59: INV1202 | GW59: INV1203 | GX59: INV1204 | GY59: INV1205 | GZ59: INV1206 | HA59: INV1207 | HB59: INV1208 | HC59: INV1209 | HD59: INV1210 | HE59: INV1211 | HF59: INV1212 | HG59: INV1213 | HH59: INV1214 | HI59: INV1215 | HJ59: INV1216 | HK59: INV1217 | HL59: INV1218 | HM59: INV1219 | HN59: INV1220 | HO59: INV1221 | HP59: INV1222 | HQ59: INV1223 | HR59: INV1224 | HS59: INV1225 | HT59: INV1226 | HU59: INV1227 | HV59: INV1228 | HW59: INV1229 | HX59: INV1230 | HY59: INV1231 | HZ59: INV1232 | IA59: INV1233 | IB59: INV1234 | IC59: INV1235 | ID59: INV1236 | IE59: INV1237 | IF59: INV1238 | IG59: INV1239 | IH59: INV1240 | II59: INV1241 | IJ59: INV1242 | IK59: INV1243 | IL59: INV1244 | IM59: INV1245 | IN59: INV1246 | IO59: INV1247 | IP59: INV1248 | IQ59: INV1249 | IR59: INV1250 | IS59: INV1251 | IT59: INV1252 | IU59: INV1253 | IV59: INV1254 | IW59: INV1255 | IX59: INV1256 | IY59: INV1257 | IZ59: INV1258 | JA59: INV1259 | JB59: INV1260 | JC59: INV1261 | JD59: INV1262 | JE59: INV1263 | JF59: INV1264 | JG59: INV1265 | JH59: INV1267 | JI59: INV1268 | JJ59: INV1269 | JK59: INV1270 | JL59: INV1271 | JM59: INV1272 | JN59: INV1273 | JO59: INV1274 | JP59: INV1275 | JQ59: INV1276 | JR59: INV1277 | JS59: INV1278 | JT59: INV1279 | JU59: INV1280 | JV59: INV1281 | JW59: INV1282 | JX59: INV1283 | JY59: INV1284 | JZ59: INV1285 | KA59: INV1286 | KB59: INV1287 | KC59: INV1288 | KD59: INV1289 | KE59: INV1290 | KF59: INV1291 | KG59: INV1292 | KH59: INV1293 | KI59: INV1294 | KJ59: INV1295 | KK59: INV1296 | KL59: INV1297 | KM59: INV1298 | KN59: INV1299 | KO59: INV1300 | KP59: INV1301 | KQ59: INV1302 | KR59: INV1303 | KS59: INV1304 | KT59: INV1305 | KU59: INV1306 | KV59: INV1307 | KW59: INV1308 | KX59: INV1309 | KY59: INV1310 | KZ59: INV1311 | LA59: INV1312 | LB59: INV1313 | LC59: INV1314 | LD59: INV1315 | LE59: INV1316 | LF59: INV1317 | LG59: INV1318 | LH59: INV1319 | LI59: INV1320 | LJ59: INV1321 | LK59: INV1322 | LL59: INV1323 | LM59: INV1324 | LN59: INV1325 | LO59: INV1326 | LP59: INV1327 | LQ59: INV1328 | LR59: INV1329 | LS59: INV1330 | LT59: INV1331 | LU59: INV1332 | LV59: INV1333 | LW59: INV1334 | LX59: INV1335 | LY59: INV1336 | LZ59: INV1337 | MA59: INV1338 | MB59: INV1339 | MC59: INV1340 | MD59: INV1341 | ME59: INV1342 | MF59: INV1343 | MG59: INV1344 | MH59: INV1345 | MI59: INV1346 | MJ59: INV1347 | MK59: INV1348 | ML59: INV1349 | MM59: INV1350 | MN59: INV1351 | MO59: INV1352 | MP59: INV1353 | MQ59: INV1355 | MR59: INV1356 | MS59: INV1357 | MT59: INV1358 | MU59: INV1359 | MV59: INV1360 | MW59: INV1362 | MX59: INV1363 | MY59: INV1364 | MZ59: INV1365 | NA59: INV1366 | NB59: INV1367 | NC59: INV1368 | ND59: INV1369 | NE59: INV1370 | NF59: INV1371 | NG59: INV1372 | NH59: INV1373 | NI59: INV1374 | NJ59: INV1375 | NK59: INV1376 | NL59: INV1377 | NM59: INV1378 | NN59: INV1379 | NO59: INV1380 | NP59: INV1381 | NQ59: INV1382 | NR59: INV1383 | NS59: INV1384 | NT59: INV1385 | NU59: INV1386 | NV59: INV1387 | NW59: INV1388 | NX59: INV1389 | NY59: INV1390 | NZ59: INV1391 | OA59: INV1392 | OB59: INV1393 | OC59: INV1394 | OD59: INV1395 | OE59: INV1396 | OF59: INV1397 | OG59: INV1398 | OH59: INV1399 | OI59: INV1400 | OJ59: INV1401 | OK59: INV1402 | OL59: INV1403 | OM59: INV1404 | ON59: INV1405 | OO59: INV1406 | OP59: INV1407 | OQ59: INV1408 | OR59: INV1409 | OS59: INV1410 | OT59: INV1411 | OU59: INV1412 | OV59: INV1413 | OW59: INV1414 | OX59: INV1415 | OY59: INV1416 | OZ59: INV1417 | PA59: INV1418 | PB59: INV1419 | PC59: INV1420 | PD59: INV1421 | PE59: INV1422 | PF59: INV1423 | PG59: INV1424 | PH59: INV1425 | PI59: INV1426 | PJ59: INV1427 | PK59: INV1428 | PL59: INV1429 | PM59: INV1430 | PN59: INV1431 | PO59: INV1432 | PP59: INV1433 | PQ59: INV1434 | PR59: INV1435 | PS59: INV1436 | PT59: INV1437 | PU59: INV1438 | PV59: INV1439 | PW59: INV1440 | PX59: INV1441 | PY59: INV1442 | PZ59: INV1443 | QA59: INV1444 | QB59: INV1445 | QC59: INV1446 | QD59: INV1447 | QE59: INV1448 | QF59: INV1449 | QG59: INV1450 | QH59: INV1451 | QI59: INV1452 | QJ59: INV1453 | QK59: INV1454 | QL59: INV1455 | QM59: INV1456 | QN59: INV1457 | QO59: INV1458 | QP59: INV1459 | QQ59: INV1460 | QR59: INV1461 | QS59: INV1462 | QT59: INV1463 | QU59: INV1464 | QV59: INV1465 | QW59: INV1466 | QX59: INV1467 | QY59: INV1468 | QZ59: INV1469 | RA59: INV1470 | RB59: INV1471 | RC59: INV1472 | RD59: INV1473 | RE59: INV1474 | RF59: INV1475 | RG59: INV1476 | RH59: INV1477 | RI59: INV1478 | RJ59: INV1479 | RK59: INV1480 | RL59: INV1481 | RM59: INV1482 | RN59: INV1483 | RO59: INV1484 | RP59: INV1485 | RQ59: INV1486 | RR59: INV1487 | RS59: INV1488 | RT59: INV1489 | RU59: INV1490 | RV59: INV1491 | RW59: INV1492 | RX59: INV1493 | RY59: INV1494 | RZ59: INV1495 | SA59: INV1496 | SB59: INV1497 | SC59: INV1498 | SD59: INV1499 | SE59: INV1500 | SF59: INV1501 | SG59: INV1502 | SH59: INV1503 | SI59: INV1504 | SJ59: INV1505 | SK59: INV1506 | SL59: INV1508 | SM59: INV1509 | SN59: INV1510 | SO59: INV1511 | SP59: INV1512 | SQ59: INV1513 | SR59: INV1514 | SS59: INV1515 | ST59: INV1516 | SU59: INV1517 | SV59: INV1518 | SW59: INV1519 | SX59: INV1520 | SY59: INV1521 | SZ59: INV1522 | TA59: INV1523 | TB59: INV1524 | TC59: INV1525 | TD59: INV1526 | TE59: INV1527 | TF59: INV1528 | TG59: INV1529 | TH59: INV1530 | TI59: INV1531 | TJ59: INV1532 | TK59: INV1533 | TL59: INV1534 | TM59: INV1535 | TN59: INV1536 | TO59: INV1537 | TP59: INV1538 | TQ59: INV1539 | TR59: INV1540 | TS59: INV1541 | TT59: INV1542 | TU59: INV1543 | TV59: INV1544 | TW59: INV1545 | TX59: INV1546 | TY59: INV1547 | TZ59: INV1548 | UA59: INV1549 | UB59: INV1550 | UC59: INV1551 | UD59: INV1552 | UE59: INV1553 | UF59: INV1554 | UG59: INV1555 | UH59: INV1556 | UI59: INV1557 | UJ59: INV1558 | UK59: INV1560 | UL59: INV1561 | UM59: INV1562 | UN59: INV1563 | UO59: INV1564 | UP59: INV1565 | UQ59: INV1566 | UR59: INV1567 | US59: INV1568 | UT59: INV1569 | UU59: INV1570 | UV59: INV1571 | UW59: INV1572 | UX59: INV1573 | UY59: INV1574 | UZ59: INV1575 | VA59: INV1576 | VB59: INV1577 | VC59: INV1578 | VD59: INV1579 | VE59: INV1580 | VF59: INV1581 | VG59: INV1582 | VH59: INV1583 | VI59: INV1584 | VJ59: INV1585 | VK59: INV1586 | VL59: INV1587 | VM59: INV1588 | VN59: INV1589 | VO59: INV1590 | VP59: INV1591 | VQ59: INV1592 | VR59: INV1593 | VS59: INV1594 | VT59: INV1595 | VU59: INV1596 | VV59: INV1597 | VW59: INV1598 | VX59: INV1599 | VY59: INV1600 | VZ59: INV1601 | WA59: INV1602 | WB59: INV1603 | WC59: INV1604 | WD59: INV1605 | WE59: INV1606 | WF59: INV1607 | WG59: INV1608 | WH59: INV1609 | WI59: INV1610 | WJ59: INV1611 | WK59: INV1612 | WL59: INV1613 | WM59: INV1614 | WN59: INV1615 | WO59: INV1616 | WP59: INV1617 | WQ59: INV1618 | WR59: INV1619 | WS59: INV1620 | WT59: INV1621 | WU59: INV1622 | WV59: INV1623 | WW59: INV1624 | WX59: INV1625 | WY59: INV1626 | WZ59: INV1627 | XA59: INV1628 | XB59: INV1629 | XC59: INV1630 | XD59: INV1631 | XE59: INV1632 | XF59: INV1633 | XG59: INV1634 | XH59: INV1635 | XI59: INV1636 | XJ59: INV1637 | XK59: INV1638 | XL59: INV1639 | XM59: INV1640 | XN59: INV1641 | XO59: INV1642 | XP59: INV1643 | XQ59: INV1644 | XR59: INV1645 | XS59: INV1646 | XT59: INV1647 | XU59: INV1648 | XV59: INV1649 | XW59: INV1650 | XX59: INV1651 | XY59: INV1652 | XZ59: INV1653 | YA59: INV1654 | YB59: INV1655 | YC59: INV1656 | YD59: INV1657 | YE59: INV1658 | YF59: INV1660 | YG59: INV1662 | YH59: INV1663 | YI59: INV1664 | YJ59: INV1665 | YK59: INV1666 | YL59: INV1667 | YM59: INV1668 | YN59: INV1669 | YO59: INV1670 | YP59: INV1671 | YQ59: INV1672 | YR59: INV1673 | YS59: INV1674 | YT59: INV1675 | YU59: INV1676 | YV59: INV1677 | YW59: INV1678 | YX59: INV1679 | YY59: INV1680 | YZ59: INV1681 | ZA59: INV1682 | ZB59: INV1683 | ZC59: INV1684 | ZD59: INV1685 | ZE59: INV1686 | ZF59: INV1687 | ZG59: INV1688 | ZH59: INV1689 | ZI59: INV1690 | ZJ59: INV1691 | ZK59: INV1692 | ZL59: INV1693 | ZM59: INV1694 | ZN59: INV1695 | ZO59: INV1696 | ZP59: INV1697 | ZQ59: INV1698 | ZR59: INV1699 | ZS59: INV1700 | ZT59: INV1701 | ZU59: INV1702 | ZV59: INV1703 | ZW59: INV1704 | ZX59: INV1705 | ZY59: INV1706 | ZZ59: INV1707 | AAA59: INV1708 | AAB59: INV1709 | AAC59: INV1710 | AAD59: INV1711 | AAE59: INV1712 | AAF59: INV1713 | AAG59: INV1714 | AAH59: INV1715 | AAI59: INV1716 | AAJ59: INV1717 | AAK59: INV1718 | AAL59: INV1719 | AAM59: INV1720 | AAN59: INV1721 | AAO59: INV1722 | AAP59: INV1723 | AAQ59: INV1724 | AAR59: INV1725 | AAS59: INV1726 | AAT59: INV1727 | AAU59: INV1728 | AAV59: INV1729 | AAW59: INV1730 | AAX59: INV1731 | AAY59: INV1732 | AAZ59: INV1733 | ABA59: INV1734 | ABB59: INV1735 | ABC59: INV1736 | ABD59: INV1737 | ABE59: INV1738 | ABF59: INV1739 | ABG59: INV1740 | ABH59: INV1741 | ABI59: INV1742 | ABJ59: INV1743 | ABK59: INV1744 | ABL59: INV1745 | ABM59: INV1746 | ABN59: INV1747 | ABO59: INV1748 | ABP59: INV1749 | ABQ59: INV1750 | ABR59: INV1751 | ABS59: INV1752 | ABT59: INV1753 | ABU59: INV1754 | ABV59: INV1755 | ABW59: INV1756 | ABX59: INV1757 | ABY59: INV1758 | ABZ59: INV1759 | ACA59: INV1760 | ACB59: INV1761 | ACC59: INV1762 | ACD59: INV1763 | ACE59: INV1764 | ACF59: INV1765 | ACG59: INV1766 | ACH59: INV1767 | ACI59: INV1768 | ACJ59: INV1769 | ACK59: INV1770 | ACL59: INV1771 | ACM59: INV1772 | ACN59: INV1773 | ACO59: INV1774 | ACP59: INV1775 | ACQ59: INV1776 | ACR59: INV1777 | ACS59: INV1778 | ACT59: INV1779 | ACU59: INV1780 | ACV59: INV1781 | ACW59: INV1782 | ACX59: INV1783 | ACY59: INV1784 | ACZ59: INV1785 | ADA59: INV1786 | ADB59: INV1787 | ADC59: INV1788 | ADD59: INV1789 | ADE59: INV1790 | ADF59: INV1791 | ADG59: INV1792 | ADH59: INV1793 | ADI59: INV1794 | ADJ59: INV1795 | ADK59: INV1796 | ADL59: INV1797 | ADM59: INV1798 | ADN59: INV1799 | ADO59: INV1800 | ADP59: INV1801 | ADQ59: INV1802 | ADR59: INV1803 | ADS59: INV1804 | ADT59: INV1805 | ADU59: INV1806 | ADV59: INV1807 | ADW59: INV1808 | ADX59: INV1809 | ADY59: INV1810 | ADZ59: INV1811 | AEA59: INV1812 | AEB59: INV1813 | AEC59: INV1814 | AED59: INV1815 | AEE59: INV1816 | AEF59: INV1818 | AEG59: INV1819 | AEH59: INV1820 | AEI59: INV1821 | AEJ59: INV1822 | AEK59: INV1823 | AEL59: INV1824 | AEM59: INV1825 | AEN59: INV1826 | AEO59: INV1827 | AEP59: INV1828 | AEQ59: INV1829 | AER59: INV1830 | AES59: INV1831 | AET59: INV1832 | AEU59: INV1833 | AEV59: INV1834 | AEW59: INV1835 | AEX59: INV1836 | AEY59: INV1837 | AEZ59: INV1838 | AFA59: INV1839 | AFB59: INV1840 | AFC59: INV1841 | AFD59: INV1842 | AFE59: INV1843 | AFF59: INV1844 | AFG59: INV1845 | AFH59: INV1846 | AFI59: INV1847 | AFJ59: INV1848 | AFK59: INV1849 | AFL59: INV1850 | AFM59: INV1851 | AFN59: INV1852 | AFO59: INV1853 | AFP59: INV1854 | AFQ59: INV1855 | AFR59: INV1856 | AFS59: INV1857 | AFT59: INV1858 | AFU59: INV1859 | AFV59: INV1860 | AFW59: INV1861 | AFX59: INV1862 | AFY59: INV1863 | AFZ59: INV1864 | AGA59: INV1865 | AGB59: INV1866 | AGC59: INV1867 | AGD59: INV1868 | AGE59: INV1869 | AGF59: INV1870 | AGG59: INV1871 | AGH59: INV1872 | AGI59: INV1873 | AGJ59: INV1874 | AGK59: INV1875 | AGL59: INV1876 | AGM59: INV1877 | AGN59: INV1878 | AGO59: INV1880 | AGP59: INV1881 | AGQ59: INV1882 | AGR59: INV1883 | AGS59: INV1884 | AGT59: INV1885 | AGU59: INV1886 | AGV59: INV1887 | AGW59: INV1888 | AGX59: INV1889 | AGY59: INV1890 | AGZ59: INV1891 | AHA59: INV1892 | AHB59: INV1893 | AHC59: INV1894 | AHD59: INV1895 | AHE59: INV1896 | AHF59: INV1897 | AHG59: INV1898 | AHH59: INV1899 | AHI59: INV1900 | AHJ59: INV1901 | AHK59: INV1902 | AHL59: INV1903 | AHM59: INV1904 | AHN59: INV1905 | AHO59: INV1906 | AHP59: INV1907 | AHQ59: INV1908 | AHR59: INV1909 | AHS59: INV1910 | AHT59: INV1911 | AHU59: INV1912 | AHV59: INV1913 | AHW59: INV1914 | AHX59: INV1915 | AHY59: INV1916 | AHZ59: INV1917 | AIA59: INV1918 | AIB59: INV1919 | AIC59: INV1920 | AID59: INV1921 | AIE59: INV1922 | AIF59: INV1923 | AIG59: INV1924 | AIH59: INV1925 | AII59: INV1926 | AIJ59: INV1927 | AIK59: INV1928 | AIL59: INV1929 | AIM59: INV1930 | AIN59: INV1931 | AIO59: INV1932 | AIP59: INV1933 | AIQ59: INV1934 | AIR59: INV1935 | AIS59: INV1936 | AIT59: INV1937 | AIU59: INV1938 | AIV59: INV1939 | AIW59: INV1940 | AIX59: INV1941 | AIY59: INV1942 | AIZ59: INV1943 | AJA59: INV1944 | AJB59: INV1945 | AJC59: INV1946 | AJD59: INV1947 | AJE59: INV1948 | AJF59: INV1949 | AJG59: INV1950 | AJH59: INV1951 | AJI59: INV1952 | AJJ59: INV1953 | AJK59: INV1954 | AJL59: INV1955 | AJM59: INV1956 | AJN59: INV1957 | AJO59: INV1958 | AJP59: INV1959 | AJQ59: INV1960 | AJR59: INV1961 | AJS59: INV1962 | AJT59: INV1963 | AJU59: INV1964 | AJV59: INV1965 | AJW59: INV1966 | AJX59: INV1967 | AJY59: INV1968 | AJZ59: INV1969 | AKA59: INV1970 | AKB59: INV1972 | AKC59: INV1973 | AKD59: INV1974 | AKE59: INV1975 | AKF59: INV1976 | AKG59: INV1977 | AKH59: INV1978 | AKI59: INV1979 | AKJ59: INV1980 | AKK59: INV1981 | AKL59: INV1982 | AKM59: INV1983 | AKN59: INV1984 | AKO59: INV1985 | AKP59: INV1986 | AKQ59: INV1987 | AKR59: INV1988 | AKS59: INV1990 | AKT59: INV1991 | AKU59: INV1992 | AKV59: INV1993 | AKW59: INV1994 | AKX59: INV1995 | AKY59: INV1996 | AKZ59: INV1997 | ALA59: INV1998 | ALB59: INV1999 | ALC59: INV2000 | ALD59: INV2001 | ALE59: INV2002 | ALF59: INV2003 | ALG59: INV2004 | ALH59: INV2005 | ALI59: INV2006 | ALJ59: INV2007 | ALK59: INV2008 | ALL59: INV2009 | ALM59: INV2010 | ALN59: INV2011 | ALO59: INV2012 | ALP59: INV2013 | ALQ59: INV2014 | ALR59: INV2015 | ALS59: INV2016 | ALT59: INV2017 | ALU59: INV2018 | ALV59: INV2019 | ALW59: INV2020 | ALX59: INV2021 | ALY59: INV2022 | ALZ59: INV2023 | AMA59: INV2024 | AMB59: INV2025 | AMC59: INV2026 | AMD59: INV2027 | AME59: INV2028 | AMF59: INV2029 | AMG59: INV2030 | AMH59: INV2031 | AMI59: INV2032 | AMJ59: INV2033 | AMK59: INV2034 | AML59: INV2035 | AMM59: INV2036 | AMN59: INV2037 | AMO59: INV2038 | AMP59: INV2039 | AMQ59: INV2040 | AMR59: INV2041 | AMS59: INV2042 | AMT59: INV2043 | AMU59: INV2044 | AMV59: INV2045 | AMW59: INV2046 | AMX59: INV2047 | AMY59: INV2048 | AMZ59: INV2049 | ANA59: INV2050 | ANB59: INV2051 | ANC59: INV2052 | AND59: INV2053 | ANE59: INV2054 | ANF59: INV2055 | ANG59: INV2056 | ANH59: INV2057 | ANI59: INV2058 | ANJ59: INV2059 | ANK59: INV2060 | ANL59: INV2061 | ANM59: INV2062 | ANN59: INV2063 | ANO59: INV2064 | ANP59: INV2065 | ANQ59: INV2066 | ANR59: INV2067 | ANS59: INV2068 | ANT59: INV2069 | ANU59: INV2070 | ANV59: INV2071 | ANW59: INV2072 | ANX59: INV2073 | ANY59: INV2074 | ANZ59: INV2075 | AOA59: INV2076 | AOB59: INV2077 | AOC59: INV2078 | AOD59: INV2079 | AOE59: INV2080 | AOF59: INV2081 | AOG59: INV2082 | AOH59: INV2083 | AOI59: INV2084 | AOJ59: INV2085 | AOK59: INV2086 | AOL59: INV2087 | AOM59: INV2088 | AON59: INV2089 | AOO59: INV2090 | AOP59: INV2091 | AOQ59: INV2092 | AOR59: INV2093 | AOS59: INV2094 | AOT59: INV2095 | AOU59: INV2096 | AOV59: INV2097 | AOW59: INV2098 | AOX59: INV2099 | AOY59: INV2100 | AOZ59: INV2101 | APA59: INV2102 | APB59: INV2103 | APC59: INV2104 | APD59: INV2105 | APE59: INV2106 | APF59: INV2107 | APG59: INV2108 | APH59: INV2109 | API59: INV2110 | APJ59: INV2111 | APK59: INV2112 | APL59: INV2113 | APM59: INV2114 | APN59: INV2115 | APO59: INV2116 | APP59: INV2117 | APQ59: INV2118 | APR59: INV2119 | APS59: INV2120 | APT59: INV2121 | APU59: INV2122 | APV59: INV2123 | APW59: INV2124 | APX59: INV2125 | APY59: INV2126 | APZ59: INV2127 | AQA59: INV2128 | AQB59: INV2129 | AQC59: INV2130 | AQD59: INV2131 | AQE59: INV2132 | AQF59: INV2133 | AQG59: INV2134 | AQH59: INV2135 | AQI59: INV2136 | AQJ59: INV2137 | AQK59: INV2138 | AQL59: INV2139 | AQM59: INV2140 | AQN59: INV2141 | AQO59: INV2142 | AQP59: INV2143 | AQQ59: INV2144 | AQR59: INV2145 | AQS59: INV2146 | AQT59: INV2148 | AQU59: INV2149 | AQV59: INV2150 | AQW59: INV2151 | AQX59: INV2152 | AQY59: INV2154 | AQZ59: INV2155 | ARA59: INV2156 | ARB59: INV2157 | ARC59: INV2158 | ARD59: INV2159 | ARE59: INV2160 | ARF59: INV2161 | ARG59: INV2162 | ARH59: INV2163 | ARI59: INV2164 | ARJ59: INV2165 | ARK59: INV2166 | ARL59: INV2167 | ARM59: INV2168 | ARN59: INV2169 | ARO59: INV2170 | ARP59: INV2171 | ARQ59: INV2172 | ARR59: INV2173 | ARS59: INV2174 | ART59: INV2175 | ARU59: INV2176 | ARV59: INV2177 | ARW59: INV2178 | ARX59: INV2179 | ARY59: INV2180 | ARZ59: INV2181 | ASA59: INV2183 | ASB59: INV2184 | ASC59: INV2185 | ASD59: INV2186 | ASE59: INV2187 | ASF59: INV2188 | ASG59: INV2189 | ASH59: INV2190 | ASI59: INV2191 | ASJ59: INV2192 | ASK59: INV2193 | ASL59: INV2194 | ASM59: INV2195 | ASN59: INV2196 | ASO59: INV2197 | ASP59: INV2198 | ASQ59: INV2199 | ASR59: INV2200 | ASS59: INV2201 | AST59: INV2202 | ASU59: INV2203 | ASV59: INV2204 | ASW59: INV2205 | ASX59: INV2206 | ASY59: INV2207 | ASZ59: INV2208 | ATA59: INV2209 | ATB59: INV2210 | ATC59: INV2211 | ATD59: INV2212 | ATE59: INV2213 | ATF59: INV2214 | ATG59: INV2215 | ATH59: INV2216 | ATI59: INV2217 | ATJ59: INV2218 | ATK59: INV2219 | ATL59: INV2220 | ATM59: INV2221 | ATN59: INV2222 | ATO59: INV2223 | ATP59: INV2224 | ATQ59: INV2225 | ATR59: INV2226 | ATS59: INV2227 | ATT59: INV2228 | ATU59: INV2229 | ATV59: INV2230 | ATW59: INV2231 | ATX59: INV2232 | ATY59: INV2233 | ATZ59: INV2234 | AUA59: INV2235 | AUB59: INV2236 | AUC59: INV2237 | AUD59: INV2238 | AUE59: INV2239 | AUF59: INV2240 | AUG59: INV2241 | AUH59: INV2242 | AUI59: INV2243 | AUJ59: INV2244 | AUK59: INV2245 | AUL59: INV2246 | AUM59: INV2247 | AUN59: INV2248 | AUO59: INV2249 | AUP59: INV2250 | AUQ59: INV2251 | AUR59: INV2252 | AUS59: INV2253 | AUT59: INV2254 | AUU59: INV2255 | AUV59: INV2256 | AUW59: INV2257 | AUX59: INV2258 | AUY59: INV2259 | AUZ59: INV2260 | AVA59: INV2261 | AVB59: INV2262 | AVC59: INV2263 | AVD59: INV2264 | AVE59: INV2265 | AVF59: INV2266 | AVG59: INV2267 | AVH59: INV2268 | AVI59: INV2269 | AVJ59: INV2270 | AVK59: INV2271 | AVL59: INV2272 | AVM59: INV2273 | AVN59: INV2274 | AVO59: INV2275 | AVP59: INV2276 | AVQ59: INV2277 | AVR59: INV2278 | AVS59: INV2279 | AVT59: INV2280 | AVU59: INV2281 | AVV59: INV2282 | AVW59: INV2283 | AVX59: INV2284 | AVY59: INV2285 | AVZ59: INV2286 | AWA59: INV2287 | AWB59: INV2288 | AWC59: INV2289 | AWD59: INV2290 | AWE59: INV2291 | AWF59: INV2292 | AWG59: INV2293 | AWH59: INV2294 | AWI59: INV2295 | AWJ59: INV2296 | AWK59: INV2297 | AWL59: INV2298 | AWM59: INV2299 | AWN59: INV2300 | AWO59: INV2301 | AWP59: INV2302 | AWQ59: INV2303 | AWR59: INV2304 | AWS59: INV2305 | AWT59: INV2306 | AWU59: INV2307 | AWV59: INV2308 | AWW59: INV2309 | AWX59: INV2310 | AWY59: INV2311 | AWZ59: INV2312 | AXA59: INV2313 | AXB59: INV2314 | AXC59: INV2315 | AXD59: INV2316 | AXE59: INV2317 | AXF59: INV2318 | AXG59: INV2319 | AXH59: INV2320 | AXI59: INV2321 | AXJ59: INV2322 | AXK59: INV2323 | AXL59: INV2325 | AXM59: INV2326 | AXN59: INV2327 | AXO59: INV2328 | AXP59: INV2329 | AXQ59: INV2330 | AXR59: INV2331 | AXS59: INV2332 | AXT59: INV2333 | AXU59: INV2334 | AXV59: INV2335 | AXW59: INV2336 | AXX59: INV2337 | AXY59: INV2338 | AXZ59: INV2339 | AYA59: INV2340 | AYB59: INV2341 | AYC59: INV2342 | AYD59: INV2343 | AYE59: INV2344 | AYF59: INV2345 | AYG59: INV2346 | AYH59: INV2347 | AYI59: INV2348 | AYJ59: INV2349 | AYK59: INV2350 | AYL59: INV2351 | AYM59: INV2352 | AYN59: INV2353 | AYO59: INV2354 | AYP59: INV2355 | AYQ59: INV2356 | AYR59: INV2357 | AYS59: INV2358 | AYT59: INV2359 | AYU59: INV2360 | AYV59: INV2361 | AYW59: INV2362 | AYX59: INV2363 | AYY59: INV2364 | AYZ59: INV2365 | AZA59: INV2366 | AZB59: INV2367 | AZC59: INV2368 | AZD59: INV2369 | AZE59: INV2370 | AZF59: INV2371 | AZG59: INV2372 | AZH59: INV2373 | AZI59: INV2374 | AZJ59: INV2375 | AZK59: INV2376 | AZL59: INV2377 | AZM59: INV2378 | AZN59: INV2379 | AZO59: INV2380 | AZP59: INV2381 | AZQ59: INV2382 | AZR59: INV2383 | AZS59: INV2384 | AZT59: INV2385 | AZU59: INV2386 | AZV59: INV2387 | AZW59: INV2388 | AZX59: INV2389 | AZY59: INV2390 | AZZ59: INV2391 | BAA59: INV2392 | BAB59: INV2393 | BAC59: INV2394 | BAD59: INV2395 | BAE59: INV2396 | BAF59: INV2397 | BAG59: INV2398 | BAH59: INV2399 | BAI59: INV2400 | BAJ59: INV2401 | BAK59: INV2402 | BAL59: INV2403 | BAM59: INV2404 | BAN59: INV2405 | BAO59: INV2406 | BAP59: INV2407 | BAQ59: INV2408 | BAR59: INV2409 | BAS59: INV2410 | BAT59: INV2411 | BAU59: INV2412 | BAV59: INV2413 | BAW59: INV2414 | BAX59: INV2416 | BAY59: INV2417 | BAZ59: INV2418 | BBA59: INV2419 | BBB59: INV2420 | BBC59: INV2421 | BBD59: INV2422 | BBE59: INV2423 | BBF59: INV2424 | BBG59: INV2425 | BBH59: INV2426 | BBI59: INV2427 | BBJ59: INV2428 | BBK59: INV2429 | BBL59: INV2430 | BBM59: INV2431 | BBN59: INV2432 | BBO59: INV2433 | BBP59: INV2434 | BBQ59: INV2435 | BBR59: INV2436 | BBS59: INV2437 | BBT59: INV2438 | BBU59: INV2439 | BBV59: INV2440 | BBW59: INV2441 | BBX59: INV2442 | BBY59: INV2444 | BBZ59: INV2445 | BCA59: INV2446 | BCB59: INV2447 | BCC59: INV2448 | BCD59: INV2449 | BCE59: INV2450 | BCF59: INV2451 | BCG59: INV2452 | BCH59: INV2453 | BCI59: INV2454 | BCJ59: INV2455 | BCK59: INV2456 | BCL59: INV2457 | BCM59: INV2458 | BCN59: INV2459 | BCO59: INV2460 | BCP59: INV2461 | BCQ59: INV2462 | BCR59: INV2463 | BCS59: INV2464 | BCT59: INV2465 | BCU59: INV2466 | BCV59: INV2467 | BCW59: INV2468 | BCX59: INV2469 | BCY59: INV2470 | BCZ59: INV2471 | BDA59: INV2472 | BDB59: INV2473 | BDC59: INV2474 | BDD59: INV2475 | BDE59: INV2476 | BDF59: INV2477 | BDG59: INV2478 | BDH59: INV2479 | BDI59: INV2480 | BDJ59: INV2481 | BDK59: INV2482 | BDL59: INV2483 | BDM59: INV2484 | BDN59: INV2485 | BDO59: INV2486 | BDP59: INV2487 | BDQ59: INV2488 | BDR59: INV2489 | BDS59: INV2490 | BDT59: INV2491 | BDU59: INV2492 | BDV59: INV2493 | BDW59: INV2494 | BDX59: INV2495 | BDY59: INV2496 | BDZ59: INV2497 | BEA59: INV2498 | BEB59: INV2499 | BEC59: INV2500 | BED59: INV2501 | BEE59: INV2502 | BEF59: INV2503 | BEG59: INV2504 | BEH59: INV2505 | BEI59: INV2506 | BEJ59: INV2507 | BEK59: INV2508 | BEL59: INV2509 | BEM59: INV2510 | BEN59: INV2511 | BEO59: INV2512 | BEP59: INV2513 | BEQ59: INV2514 | BER59: INV2515 | BES59: INV2516 | BET59: INV2517 | BEU59: INV2518 | BEV59: INV2519 | BEW59: INV2520 | BEX59: INV2521 | BEY59: INV2522 | BEZ59: INV2523 | BFA59: INV2524 | BFB59: INV2525 | BFC59: INV2526 | BFD59: INV2527 | BFE59: INV2528 | BFF59: INV2529 | BFG59: INV2530 | BFH59: INV2531 | BFI59: INV2532 | BFJ59: INV2533 | BFK59: INV2534 | BFL59: INV2535 | BFM59: INV2536 | BFN59: INV2537 | BFO59: INV2538 | BFP59: INV2539 | BFQ59: INV2540 | BFR59: INV2541 | BFS59: INV2542 | BFT59: INV2543 | BFU59: INV2544 | BFV59: INV2545 | BFW59: INV2546 | BFX59: INV2547 | BFY59: INV2548 | BFZ59: INV2549 | BGA59: INV2550 | BGB59: INV2551 | BGC59: INV2552 | BGD59: INV2553 | BGE59: INV2554 | BGF59: INV2555 | BGG59: INV2556 | BGH59: INV2557 | BGI59: INV2558 | BGJ59: INV2559 | BGK59: INV2560 | BGL59: INV2561 | BGM59: INV2562 | BGN59: INV2563 | BGO59: INV2564 | BGP59: INV2565 | BGQ59: INV2566 | BGR59: INV2567 | BGS59: INV2568 | BGT59: INV2569 | BGU59: INV2570 | BGV59: INV2571 | BGW59: INV2572 | BGX59: INV2573 | BGY59: INV2574 | BGZ59: INV2575 | BHA59: INV2576 | BHB59: INV2577 | BHC59: INV2578 | BHD59: INV2579 | BHE59: INV2580 | BHF59: INV2581 | BHG59: INV2582 | BHH59: INV2583 | BHI59: INV2584 | BHJ59: INV2585 | BHK59: INV2586 | BHL59: INV2587 | BHM59: INV2588 | BHN59: INV2589 | BHO59: INV2590 | BHP59: INV2591 | BHQ59: INV2592 | BHR59: INV2593 | BHS59: INV2594 | BHT59: INV2595 | BHU59: INV2596 | BHV59: INV2597 | BHW59: INV2598 | BHX59: INV2599 | BHY59: INV2601 | BHZ59: INV2602 | BIA59: INV2603 | BIB59: INV2604 | BIC59: INV2605 | BID59: INV2606 | BIE59: INV2607 | BIF59: INV2608 | BIG59: INV2609 | BIH59: INV2610 | BII59: INV2611 | BIJ59: INV2612 | BIK59: INV2613 | BIL59: INV2614 | BIM59: INV2615 | BIN59: INV2616 | BIO59: INV2617 | BIP59: INV2618 | BIQ59: INV2619 | BIR59: INV2620 | BIS59: INV2621 | BIT59: INV2622 | BIU59: INV2623 | BIV59: INV2624 | BIW59: INV2625 | BIX59: INV2626 | BIY59: INV2627 | BIZ59: INV2628 | BJA59: INV2629 | BJB59: INV2630 | BJC59: INV2631 | BJD59: INV2632 | BJE59: INV2633 | BJF59: INV2634 | BJG59: INV2635 | BJH59: INV2636 | BJI59: INV2637 | BJJ59: INV2638 | BJK59: INV2639 | BJL59: INV2640 | BJM59: INV2641 | BJN59: INV2642 | BJO59: INV2643 | BJP59: INV2644 | BJQ59: INV2645 | BJR59: INV2646 | BJS59: INV2647 | BJT59: INV2648 | BJU59: INV2649 | BJV59: INV2650 | BJW59: INV2651 | BJX59: INV2652 | BJY59: INV2653 | BJZ59: INV2654 | BKA59: INV2655 | BKB59: INV2656 | BKC59: INV2657 | BKD59: INV2658 | BKE59: INV2659 | BKF59: INV2660 | BKG59: INV2661 | BKH59: INV2662 | BKI59: INV2663 | BKJ59: INV2664 | BKK59: INV2665 | BKL59: INV2666 | BKM59: INV2667 | BKN59: INV2668 | BKO59: INV2669 | BKP59: INV2670 | BKQ59: INV2671 | BKR59: INV2672 | BKS59: INV2673 | BKT59: INV2674 | BKU59: INV2675 | BKV59: INV2676 | BKW59: INV2677 | BKX59: INV2678 | BKY59: INV2679 | BKZ59: INV2680 | BLA59: INV2681 | BLB59: INV2682 | BLC59: INV2683 | BLD59: INV2684 | BLE59: INV2685 | BLF59: INV2686 | BLG59: INV2687 | BLH59: INV2688 | BLI59: INV2689 | BLJ59: INV2690 | BLK59: INV2691 | BLL59: INV2692 | BLM59: INV2693 | BLN59: INV2694 | BLO59: INV2695 | BLP59: INV2696 | BLQ59: INV2697 | BLR59: INV2698 | BLS59: INV2699 | BLT59: INV2700 | BLU59: INV2701 | BLV59: INV2702 | BLW59: INV2703 | BLX59: INV2704 | BLY59: INV2705 | BLZ59: INV2706 | BMA59: INV2707 | BMB59: INV2708 | BMC59: INV2709 | BMD59: INV2710 | BME59: INV2711 | BMF59: INV2712 | BMG59: INV2713 | BMH59: INV2714 | BMI59: INV2716 | BMJ59: INV2717 | BMK59: INV2718 | BML59: INV2719 | BMM59: INV2720 | BMN59: INV2721 | BMO59: INV2722 | BMP59: INV2723 | BMQ59: INV2724 | BMR59: INV2725 | BMS59: INV2726 | BMT59: INV2727 | BMU59: INV2728 | BMV59: INV2729 | BMW59: INV2730 | BMX59: INV2731 | BMY59: INV2732 | BMZ59: INV2733 | BNA59: INV2734 | BNB59: INV2735 | BNC59: INV2736 | BND59: INV2737 | BNE59: INV2738 | BNF59: INV2739 | BNG59: INV2740 | BNH59: INV2741 | BNI59: INV2742 | BNJ59: INV2743 | BNK59: INV2744 | BNL59: INV2745 | BNM59: INV2746 | BNN59: INV2747 | BNO59: INV2748 | BNP59: INV2749 | BNQ59: INV2750 | BNR59: INV2751 | BNS59: INV2752 | BNT59: INV2753 | BNU59: INV2754 | BNV59: INV2755 | BNW59: INV2756 | BNX59: INV2757 | BNY59: INV2758 | BNZ59: INV2759 | BOA59: INV2760 | BOB59: INV2761 | BOC59: INV2762 | BOD59: INV2763 | BOE59: INV2764 | BOF59: INV2765 | BOG59: INV2766 | BOH59: INV2767 | BOI59: INV2768 | BOJ59: INV2769 | BOK59: INV2770 | BOL59: INV2771 | BOM59: INV2772 | BON59: INV2773 | BOO59: INV2774 | BOP59: INV2775 | BOQ59: INV2776 | BOR59: INV2777 | BOS59: INV2778 | BOT59: INV2779 | BOU59: INV2780 | BOV59: INV2781 | BOW59: INV2782 | BOX59: INV2783 | BOY59: INV2784 | BOZ59: INV2785 | BPA59: INV2786 | BPB59: INV2787 | BPC59: INV2788 | BPD59: INV2789 | BPE59: INV2790 | BPF59: INV2791 | BPG59: INV2792 | BPH59: INV2793 | BPI59: INV2794 | BPJ59: INV2795 | BPK59: INV2796 | BPL59: INV2797 | BPM59: INV2798 | BPN59: INV2799 | BPO59: INV2800 | BPP59: INV2801 | BPQ59: INV2802 | BPR59: INV2803 | BPS59: INV2804 | BPT59: INV2805 | BPU59: INV2806 | BPV59: INV2807 | BPW59: INV2808 | BPX59: INV2809 | BPY59: INV2810 | BPZ59: INV2811 | BQA59: INV2812 | BQB59: INV2813 | BQC59: INV2814 | BQD59: INV2815 | BQE59: INV2816 | BQF59: INV2817 | BQG59: INV2818 | BQH59: INV2819 | BQI59: INV2820 | BQJ59: INV2821 | BQK59: INV2822 | BQL59: INV2823 | BQM59: INV2824 | BQN59: INV2825 | BQO59: INV2826 | BQP59: INV2827 | BQQ59: INV2828 | BQR59: INV2829 | BQS59: INV2830 | BQT59: INV2831 | BQU59: INV2832 | BQV59: INV2833 | BQW59: INV2834 | BQX59: INV2835 | BQY59: INV2836 | BQZ59: INV2837 | BRA59: INV2838 | BRB59: INV2839 | BRC59: INV2840 | BRD59: INV2841 | BRE59: INV2842 | BRF59: INV2843 | BRG59: INV2844 | BRH59: INV2845 | BRI59: INV2846 | BRJ59: INV2847 | BRK59: INV2848 | BRL59: INV2849 | BRM59: INV2850 | BRN59: INV2851 | BRO59: INV2852 | BRP59: INV2853 | BRQ59: INV2854 | BRR59: INV2855 | BRS59: INV2856 | BRT59: INV2857 | BRU59: INV2858 | BRV59: INV2859 | BRW59: INV2860 | BRX59: INV2861 | BRY59: INV2862 | BRZ59: INV2863 | BSA59: INV2864 | BSB59: INV2865 | BSC59: INV2866 | BSD59: INV2867 | BSE59: INV2868 | BSF59: INV2869 | BSG59: INV2870 | BSH59: INV2871 | BSI59: INV2872 | BSJ59: INV2873 | BSK59: INV2874 | BSL59: INV2875 | BSM59: INV2876 | BSN59: INV2877 | BSO59: INV2878 | BSP59: INV2879 | BSQ59: INV2880 | BSR59: INV2881 | BSS59: INV2882 | BST59: INV2883 | BSU59: INV2884 | BSV59: INV2885 | BSW59: INV2886 | BSX59: INV2887 | BSY59: INV2888 | BSZ59: INV2889 | BTA59: INV2890 | BTB59: INV2891 | BTC59: INV2892 | BTD59: INV2893 | BTE59: INV2894 | BTF59: INV2895 | BTG59: INV2896 | BTH59: INV2897 | BTI59: INV2898 | BTJ59: INV2899 | BTK59: INV2900 | BTL59: INV2901 | BTM59: INV2902 | BTN59: INV2903 | BTO59: INV2904 | BTP59: INV2905 | BTQ59: INV2906 | BTR59: INV2907 | BTS59: INV2908 | BTT59: INV2909 | BTU59: INV2910 | BTV59: INV2911 | BTW59: INV2912 | BTX59: INV2913 | BTY59: INV2914 | BTZ59: INV2915 | BUA59: INV2916 | BUB59: INV2917 | BUC59: INV2918 | BUD59: INV2919 | BUE59: INV2920 | BUF59: INV2921 | BUG59: INV2922 | BUH59: INV2923 | BUI59: INV2924 | BUJ59: INV2925 | BUK59: INV2926 | BUL59: INV2927 | BUM59: INV2928 | BUN59: INV2929 | BUO59: INV2930 | BUP59: INV2931 | BUQ59: INV2933 | BUR59: INV2934 | BUS59: INV2935 | BUT59: INV2936 | BUU59: INV2937 | BUV59: INV2938 | BUW59: INV2939 | BUX59: INV2940 | BUY59: INV2941 | BUZ59: INV2942 | BVA59: INV2943 | BVB59: INV2944 | BVC59: INV2945 | BVD59: INV2946 | BVE59: INV2947 | BVF59: INV2948 | BVG59: INV2949 | BVH59: INV2950 | BVI59: INV2951 | BVJ59: INV2952 | BVK59: INV2953 | BVL59: INV2954 | BVM59: INV2955 | BVN59: INV2956 | BVO59: INV2957 | BVP59: INV2958 | BVQ59: INV2959 | BVR59: INV2960 | BVS59: INV2961 | BVT59: INV2962 | BVU59: INV2963 | BVV59: INV2964 | BVW59: INV2965 | BVX59: INV2966 | BVY59: INV2967 | BVZ59: INV2968 | BWA59: INV2969 | BWB59: INV2970 | BWC59: INV2971 | BWD59: INV2972 | BWE59: INV2973 | BWF59: INV2974 | BWG59: INV2975 | BWH59: INV2976 | BWI59: INV2977 | BWJ59: INV2978 | BWK59: INV2979 | BWL59: INV2980 | BWM59: INV2981 | BWN59: INV2982 | BWO59: INV2983 | BWP59: INV2984 | BWQ59: INV2985 | BWR59: INV2986 | BWS59: INV2987 | BWT59: INV2988 | BWU59: INV2989 | BWV59: INV2990 | BWW59: INV2991 | BWX59: INV2992 | BWY59: INV2993 | BWZ59: INV2994 | BXA59: INV2995 | BXB59: INV2996 | BXC59: INV2997 | BXD59: INV2998 | BXE59: INV2999 | BXF59: Grand Total
B60: Count of Invoice ID | C60: 1 | D60: 1 | E60: 1 | F60: 1 | G60: 1 | H60: 1 | I60: 1 | J60: 1 | K60: 1 | L60: 1 | M60: 1 | N60: 1 | O60: 1 | P60: 1 | Q60: 1 | R60: 1 | S60: 1 | T60: 1 | U60: 1 | V60: 1 | W60: 1 | X60: 1 | Y60: 1 | Z60: 1 | AA60: 1 | AB60: 1 | AC60: 1 | AD60: 1 | AE60: 1 | AF60: 1 | AG60: 1 | AH60: 1 | AI60: 1 | AJ60: 1 | AK60: 1 | AL60: 1 | AM60: 1 | AN60: 1 | AO60: 1 | AP60: 1 | AQ60: 1 | AR60: 1 | AS60: 1 | AT60: 1 | AU60: 1 | AV60: 1 | AW60: 1 | AX60: 1 | AY60: 1 | AZ60: 1 | BA60: 1 | BB60: 1 | BC60: 1 | BD60: 1 | BE60: 1 | BF60: 1 | BG60: 1 | BH60: 1 | BI60: 1 | BJ60: 1 | BK60: 1 | BL60: 1 | BM60: 1 | BN60: 1 | BO60: 1 | BP60: 1 | BQ60: 1 | BR60: 1 | BS60: 1 | BT60: 1 | BU60: 1 | BV60: 1 | BW60: 1 | BX60: 1 | BY60: 1 | BZ60: 1 | CA60: 1 | CB60: 1 | CC60: 1 | CD60: 1 | CE60: 1 | CF60: 1 | CG60: 1 | CH60: 1 | CI60: 1 | CJ60: 1 | CK60: 1 | CL60: 1 | CM60: 1 | CN60: 1 | CO60: 1 | CP60: 1 | CQ60: 1 | CR60: 1 | CS60: 1 | CT60: 1 | CU60: 1 | CV60: 1 | CW60: 1 | CX60: 1 | CY60: 1 | CZ60: 1 | DA60: 1 | DB60: 1 | DC60: 1 | DD60: 1 | DE60: 1 | DF60: 1 | DG60: 1 | DH60: 1 | DI60: 1 | DJ60: 1 | DK60: 1 | DL60: 1 | DM60: 1 | DN60: 1 | DO60: 1 | DP60: 1 | DQ60: 1 | DR60: 1 | DS60: 1 | DT60: 1 | DU60: 1 | DV60: 1 | DW60: 1 | DX60: 1 | DY60: 1 | DZ60: 1 | EA60: 1 | EB60: 1 | EC60: 1 | ED60: 1 | EE60: 1 | EF60: 1 | EG60: 1 | EH60: 1 | EI60: 1 | EJ60: 1 | EK60: 1 | EL60: 1 | EM60: 1 | EN60: 1 | EO60: 1 | EP60: 1 | EQ60: 1 | ER60: 1 | ES60: 1 | ET60: 1 | EU60: 1 | EV60: 1 | EW60: 1 | EX60: 1 | EY60: 1 | EZ60: 1 | FA60: 1 | FB60: 1 | FC60: 1 | FD60: 1 | FE60: 1 | FF60: 1 | FG60: 1 | FH60: 1 | FI60: 1 | FJ60: 1 | FK60: 1 | FL60: 1 | FM60: 1 | FN60: 1 | FO60: 1 | FP60: 1 | FQ60: 1 | FR60: 1 | FS60: 1 | FT60: 1 | FU60: 1 | FV60: 1 | FW60: 1 | FX60: 1 | FY60: 1 | FZ60: 1 | GA60: 1 | GB60: 1 | GC60: 1 | GD60: 1 | GE60: 1 | GF60: 1 | GG60: 1 | GH60: 1 | GI60: 1 | GJ60: 1 | GK60: 1 | GL60: 1 | GM60: 1 | GN60: 1 | GO60: 1 | GP60: 1 | GQ60: 1 | GR60: 1 | GS60: 1 | GT60: 1 | GU60: 1 | GV60: 1 | GW60: 1 | GX60: 1 | GY60: 1 | GZ60: 1 | HA60: 1 | HB60: 1 | HC60: 1 | HD60: 1 | HE60: 1 | HF60: 1 | HG60: 1 | HH60: 1 | HI60: 1 | HJ60: 1 | HK60: 1 | HL60: 1 | HM60: 1 | HN60: 1 | HO60: 1 | HP60: 1 | HQ60: 1 | HR60: 1 | HS60: 1 | HT60: 1 | HU60: 1 | HV60: 1 | HW60: 1 | HX60: 1 | HY60: 1 | HZ60: 1 | IA60: 1 | IB60: 1 | IC60: 1 | ID60: 1 | IE60: 1 | IF60: 1 | IG60: 1 | IH60: 1 | II60: 1 | IJ60: 1 | IK60: 1 | IL60: 1 | IM60: 1 | IN60: 1 | IO60: 1 | IP60: 1 | IQ60: 1 | IR60: 1 | IS60: 1 | IT60: 1 | IU60: 1 | IV60: 1 | IW60: 1 | IX60: 1 | IY60: 1 | IZ60: 1 | JA60: 1 | JB60: 1 | JC60: 1 | JD60: 1 | JE60: 1 | JF60: 1 | JG60: 1 | JH60: 1 | JI60: 1 | JJ60: 1 | JK60: 1 | JL60: 1 | JM60: 1 | JN60: 1 | JO60: 1 | JP60: 1 | JQ60: 1 | JR60: 1 | JS60: 1 | JT60: 1 | JU60: 1 | JV60: 1 | JW60: 1 | JX60: 1 | JY60: 1 | JZ60: 1 | KA60: 1 | KB60: 1 | KC60: 1 | KD60: 1 | KE60: 1 | KF60: 1 | KG60: 1 | KH60: 1 | KI60: 1 | KJ60: 1 | KK60: 1 | KL60: 1 | KM60: 1 | KN60: 1 | KO60: 1 | KP60: 1 | KQ60: 1 | KR60: 1 | KS60: 1 | KT60: 1 | KU60: 1 | KV60: 1 | KW60: 1 | KX60: 1 | KY60: 1 | KZ60: 1 | LA60: 1 | LB60: 1 | LC60: 1 | LD60: 1 | LE60: 1 | LF60: 1 | LG60: 1 | LH60: 1 | LI60: 1 | LJ60: 1 | LK60: 1 | LL60: 1 | LM60: 1 | LN60: 1 | LO60: 1 | LP60: 1 | LQ60: 1 | LR60: 1 | LS60: 1 | LT60: 1 | LU60: 1 | LV60: 1 | LW60: 1 | LX60: 1 | LY60: 1 | LZ60: 1 | MA60: 1 | MB60: 1 | MC60: 1 | MD60: 1 | ME60: 1 | MF60: 1 | MG60: 1 | MH60: 1 | MI60: 1 | MJ60: 1 | MK60: 1 | ML60: 1 | MM60: 1 | MN60: 1 | MO60: 1 | MP60: 1 | MQ60: 1 | MR60: 1 | MS60: 1 | MT60: 1 | MU60: 1 | MV60: 1 | MW60: 1 | MX60: 1 | MY60: 1 | MZ60: 1 | NA60: 1 | NB60: 1 | NC60: 1 | ND60: 1 | NE60: 1 | NF60: 1 | NG60: 1 | NH60: 1 | NI60: 1 | NJ60: 1 | NK60: 1 | NL60: 1 | NM60: 1 | NN60: 1 | NO60: 1 | NP60: 1 | NQ60: 1 | NR60: 1 | NS60: 1 | NT60: 1 | NU60: 1 | NV60: 1 | NW60: 1 | NX60: 1 | NY60: 1 | NZ60: 1 | OA60: 1 | OB60: 1 | OC60: 1 | OD60: 1 | OE60: 1 | OF60: 1 | OG60: 1 | OH60: 1 | OI60: 1 | OJ60: 1 | OK60: 1 | OL60: 1 | OM60: 1 | ON60: 1 | OO60: 1 | OP60: 1 | OQ60: 1 | OR60: 1 | OS60: 1 | OT60: 1 | OU60: 1 | OV60: 1 | OW60: 1 | OX60: 1 | OY60: 1 | OZ60: 1 | PA60: 1 | PB60: 1 | PC60: 1 | PD60: 1 | PE60: 1 | PF60: 1 | PG60: 1 | PH60: 1 | PI60: 1 | PJ60: 1 | PK60: 1 | PL60: 1 | PM60: 1 | PN60: 1 | PO60: 1 | PP60: 1 | PQ60: 1 | PR60: 1 | PS60: 1 | PT60: 1 | PU60: 1 | PV60: 1 | PW60: 1 | PX60: 1 | PY60: 1 | PZ60: 1 | QA60: 1 | QB60: 1 | QC60: 1 | QD60: 1 | QE60: 1 | QF60: 1 | QG60: 1 | QH60: 1 | QI60: 1 | QJ60: 1 | QK60: 1 | QL60: 1 | QM60: 1 | QN60: 1 | QO60: 1 | QP60: 1 | QQ60: 1 | QR60: 1 | QS60: 1 | QT60: 1 | QU60: 1 | QV60: 1 | QW60: 1 | QX60: 1 | QY60: 1 | QZ60: 1 | RA60: 1 | RB60: 1 | RC60: 1 | RD60: 1 | RE60: 1 | RF60: 1 | RG60: 1 | RH60: 1 | RI60: 1 | RJ60: 1 | RK60: 1 | RL60: 1 | RM60: 1 | RN60: 1 | RO60: 1 | RP60: 1 | RQ60: 1 | RR60: 1 | RS60: 1 | RT60: 1 | RU60: 1 | RV60: 1 | RW60: 1 | RX60: 1 | RY60: 1 | RZ60: 1 | SA60: 1 | SB60: 1 | SC60: 1 | SD60: 1 | SE60: 1 | SF60: 1 | SG60: 1 | SH60: 1 | SI60: 1 | SJ60: 1 | SK60: 1 | SL60: 1 | SM60: 1 | SN60: 1 | SO60: 1 | SP60: 1 | SQ60: 1 | SR60: 1 | SS60: 1 | ST60: 1 | SU60: 1 | SV60: 1 | SW60: 1 | SX60: 1 | SY60: 1 | SZ60: 1 | TA60: 1 | TB60: 1 | TC60: 1 | TD60: 1 | TE60: 1 | TF60: 1 | TG60: 1 | TH60: 1 | TI60: 1 | TJ60: 1 | TK60: 1 | TL60: 1 | TM60: 1 | TN60: 1 | TO60: 1 | TP60: 1 | TQ60: 1 | TR60: 1 | TS60: 1 | TT60: 1 | TU60: 1 | TV60: 1 | TW60: 1 | TX60: 1 | TY60: 1 | TZ60: 1 | UA60: 1 | UB60: 1 | UC60: 1 | UD60: 1 | UE60: 1 | UF60: 1 | UG60: 1 | UH60: 1 | UI60: 1 | UJ60: 1 | UK60: 1 | UL60: 1 | UM60: 1 | UN60: 1 | UO60: 1 | UP60: 1 | UQ60: 1 | UR60: 1 | US60: 1 | UT60: 1 | UU60: 1 | UV60: 1 | UW60: 1 | UX60: 1 | UY60: 1 | UZ60: 1 | VA60: 1 | VB60: 1 | VC60: 1 | VD60: 1 | VE60: 1 | VF60: 1 | VG60: 1 | VH60: 1 | VI60: 1 | VJ60: 1 | VK60: 1 | VL60: 1 | VM60: 1 | VN60: 1 | VO60: 1 | VP60: 1 | VQ60: 1 | VR60: 1 | VS60: 1 | VT60: 1 | VU60: 1 | VV60: 1 | VW60: 1 | VX60: 1 | VY60: 1 | VZ60: 1 | WA60: 1 | WB60: 1 | WC60: 1 | WD60: 1 | WE60: 1 | WF60: 1 | WG60: 1 | WH60: 1 | WI60: 1 | WJ60: 1 | WK60: 1 | WL60: 1 | WM60: 1 | WN60: 1 | WO60: 1 | WP60: 1 | WQ60: 1 | WR60: 1 | WS60: 1 | WT60: 1 | WU60: 1 | WV60: 1 | WW60: 1 | WX60: 1 | WY60: 1 | WZ60: 1 | XA60: 1 | XB60: 1 | XC60: 1 | XD60: 1 | XE60: 1 | XF60: 1 | XG60: 1 | XH60: 1 | XI60: 1 | XJ60: 1 | XK60: 1 | XL60: 1 | XM60: 1 | XN60: 1 | XO60: 1 | XP60: 1 | XQ60: 1 | XR60: 1 | XS60: 1 | XT60: 1 | XU60: 1 | XV60: 1 | XW60: 1 | XX60: 1 | XY60: 1 | XZ60: 1 | YA60: 1 | YB60: 1 | YC60: 1 | YD60: 1 | YE60: 1 | YF60: 1 | YG60: 1 | YH60: 1 | YI60: 1 | YJ60: 1 | YK60: 1 | YL60: 1 | YM60: 1 | YN60: 1 | YO60: 1 | YP60: 1 | YQ60: 1 | YR60: 1 | YS60: 1 | YT60: 1 | YU60: 1 | YV60: 1 | YW60: 1 | YX60: 1 | YY60: 1 | YZ60: 1 | ZA60: 1 | ZB60: 1 | ZC60: 1 | ZD60: 1 | ZE60: 1 | ZF60: 1 | ZG60: 1 | ZH60: 1 | ZI60: 1 | ZJ60: 1 | ZK60: 1 | ZL60: 1 | ZM60: 1 | ZN60: 1 | ZO60: 1 | ZP60: 1 | ZQ60: 1 | ZR60: 1 | ZS60: 1 | ZT60: 1 | ZU60: 1 | ZV60: 1 | ZW60: 1 | ZX60: 1 | ZY60: 1 | ZZ60: 1 | AAA60: 1 | AAB60: 1 | AAC60: 1 | AAD60: 1 | AAE60: 1 | AAF60: 1 | AAG60: 1 | AAH60: 1 | AAI60: 1 | AAJ60: 1 | AAK60: 1 | AAL60: 1 | AAM60: 1 | AAN60: 1 | AAO60: 1 | AAP60: 1 | AAQ60: 1 | AAR60: 1 | AAS60: 1 | AAT60: 1 | AAU60: 1 | AAV60: 1 | AAW60: 1 | AAX60: 1 | AAY60: 1 | AAZ60: 1 | ABA60: 1 | ABB60: 1 | ABC60: 1 | ABD60: 1 | ABE60: 1 | ABF60: 1 | ABG60: 1 | ABH60: 1 | ABI60: 1 | ABJ60: 1 | ABK60: 1 | ABL60: 1 | ABM60: 1 | ABN60: 1 | ABO60: 1 | ABP60: 1 | ABQ60: 1 | ABR60: 1 | ABS60: 1 | ABT60: 1 | ABU60: 1 | ABV60: 1 | ABW60: 1 | ABX60: 1 | ABY60: 1 | ABZ60: 1 | ACA60: 1 | ACB60: 1 | ACC60: 1 | ACD60: 1 | ACE60: 1 | ACF60: 1 | ACG60: 1 | ACH60: 1 | ACI60: 1 | ACJ60: 1 | ACK60: 1 | ACL60: 1 | ACM60: 1 | ACN60: 1 | ACO60: 1 | ACP60: 1 | ACQ60: 1 | ACR60: 1 | ACS60: 1 | ACT60: 1 | ACU60: 1 | ACV60: 1 | ACW60: 1 | ACX60: 1 | ACY60: 1 | ACZ60: 1 | ADA60: 1 | ADB60: 1 | ADC60: 1 | ADD60: 1 | ADE60: 1 | ADF60: 1 | ADG60: 1 | ADH60: 1 | ADI60: 1 | ADJ60: 1 | ADK60: 1 | ADL60: 1 | ADM60: 1 | ADN60: 1 | ADO60: 1 | ADP60: 1 | ADQ60: 1 | ADR60: 1 | ADS60: 1 | ADT60: 1 | ADU60: 1 | ADV60: 1 | ADW60: 1 | ADX60: 1 | ADY60: 1 | ADZ60: 1 | AEA60: 1 | AEB60: 1 | AEC60: 1 | AED60: 1 | AEE60: 1 | AEF60: 1 | AEG60: 1 | AEH60: 1 | AEI60: 1 | AEJ60: 1 | AEK60: 1 | AEL60: 1 | AEM60: 1 | AEN60: 1 | AEO60: 1 | AEP60: 1 | AEQ60: 1 | AER60: 1 | AES60: 1 | AET60: 1 | AEU60: 1 | AEV60: 1 | AEW60: 1 | AEX60: 1 | AEY60: 1 | AEZ60: 1 | AFA60: 1 | AFB60: 1 | AFC60: 1 | AFD60: 1 | AFE60: 1 | AFF60: 1 | AFG60: 1 | AFH60: 1 | AFI60: 1 | AFJ60: 1 | AFK60: 1 | AFL60: 1 | AFM60: 1 | AFN60: 1 | AFO60: 1 | AFP60: 1 | AFQ60: 1 | AFR60: 1 | AFS60: 1 | AFT60: 1 | AFU60: 1 | AFV60: 1 | AFW60: 1 | AFX60: 1 | AFY60: 1 | AFZ60: 1 | AGA60: 1 | AGB60: 1 | AGC60: 1 | AGD60: 1 | AGE60: 1 | AGF60: 1 | AGG60: 1 | AGH60: 1 | AGI60: 1 | AGJ60: 1 | AGK60: 1 | AGL60: 1 | AGM60: 1 | AGN60: 1 | AGO60: 1 | AGP60: 1 | AGQ60: 1 | AGR60: 1 | AGS60: 1 | AGT60: 1 | AGU60: 1 | AGV60: 1 | AGW60: 1 | AGX60: 1 | AGY60: 1 | AGZ60: 1 | AHA60: 1 | AHB60: 1 | AHC60: 1 | AHD60: 1 | AHE60: 1 | AHF60: 1 | AHG60: 1 | AHH60: 1 | AHI60: 1 | AHJ60: 1 | AHK60: 1 | AHL60: 1 | AHM60: 1 | AHN60: 1 | AHO60: 1 | AHP60: 1 | AHQ60: 1 | AHR60: 1 | AHS60: 1 | AHT60: 1 | AHU60: 1 | AHV60: 1 | AHW60: 1 | AHX60: 1 | AHY60: 1 | AHZ60: 1 | AIA60: 1 | AIB60: 1 | AIC60: 1 | AID60: 1 | AIE60: 1 | AIF60: 1 | AIG60: 1 | AIH60: 1 | AII60: 1 | AIJ60: 1 | AIK60: 1 | AIL60: 1 | AIM60: 1 | AIN60: 1 | AIO60: 1 | AIP60: 1 | AIQ60: 1 | AIR60: 1 | AIS60: 1 | AIT60: 1 | AIU60: 1 | AIV60: 1 | AIW60: 1 | AIX60: 1 | AIY60: 1 | AIZ60: 1 | AJA60: 1 | AJB60: 1 | AJC60: 1 | AJD60: 1 | AJE60: 1 | AJF60: 1 | AJG60: 1 | AJH60: 1 | AJI60: 1 | AJJ60: 1 | AJK60: 1 | AJL60: 1 | AJM60: 1 | AJN60: 1 | AJO60: 1 | AJP60: 1 | AJQ60: 1 | AJR60: 1 | AJS60: 1 | AJT60: 1 | AJU60: 1 | AJV60: 1 | AJW60: 1 | AJX60: 1 | AJY60: 1 | AJZ60: 1 | AKA60: 1 | AKB60: 1 | AKC60: 1 | AKD60: 1 | AKE60: 1 | AKF60: 1 | AKG60: 1 | AKH60: 1 | AKI60: 1 | AKJ60: 1 | AKK60: 1 | AKL60: 1 | AKM60: 1 | AKN60: 1 | AKO60: 1 | AKP60: 1 | AKQ60: 1 | AKR60: 1 | AKS60: 1 | AKT60: 1 | AKU60: 1 | AKV60: 1 | AKW60: 1 | AKX60: 1 | AKY60: 1 | AKZ60: 1 | ALA60: 1 | ALB60: 1 | ALC60: 1 | ALD60: 1 | ALE60: 1 | ALF60: 1 | ALG60: 1 | ALH60: 1 | ALI60: 1 | ALJ60: 1 | ALK60: 1 | ALL60: 1 | ALM60: 1 | ALN60: 1 | ALO60: 1 | ALP60: 1 | ALQ60: 1 | ALR60: 1 | ALS60: 1 | ALT60: 1 | ALU60: 1 | ALV60: 1 | ALW60: 1 | ALX60: 1 | ALY60: 1 | ALZ60: 1 | AMA60: 1 | AMB60: 1 | AMC60: 1 | AMD60: 1 | AME60: 1 | AMF60: 1 | AMG60: 1 | AMH60: 1 | AMI60: 1 | AMJ60: 1 | AMK60: 1 | AML60: 1 | AMM60: 1 | AMN60: 1 | AMO60: 1 | AMP60: 1 | AMQ60: 1 | AMR60: 1 | AMS60: 1 | AMT60: 1 | AMU60: 1 | AMV60: 1 | AMW60: 1 | AMX60: 1 | AMY60: 1 | AMZ60: 1 | ANA60: 1 | ANB60: 1 | ANC60: 1 | AND60: 1 | ANE60: 1 | ANF60: 1 | ANG60: 1 | ANH60: 1 | ANI60: 1 | ANJ60: 1 | ANK60: 1 | ANL60: 1 | ANM60: 1 | ANN60: 1 | ANO60: 1 | ANP60: 1 | ANQ60: 1 | ANR60: 1 | ANS60: 1 | ANT60: 1 | ANU60: 1 | ANV60: 1 | ANW60: 1 | ANX60: 1 | ANY60: 1 | ANZ60: 1 | AOA60: 1 | AOB60: 1 | AOC60: 1 | AOD60: 1 | AOE60: 1 | AOF60: 1 | AOG60: 1 | AOH60: 1 | AOI60: 1 | AOJ60: 1 | AOK60: 1 | AOL60: 1 | AOM60: 1 | AON60: 1 | AOO60: 1 | AOP60: 1 | AOQ60: 1 | AOR60: 1 | AOS60: 1 | AOT60: 1 | AOU60: 1 | AOV60: 1 | AOW60: 1 | AOX60: 1 | AOY60: 1 | AOZ60: 1 | APA60: 1 | APB60: 1 | APC60: 1 | APD60: 1 | APE60: 1 | APF60: 1 | APG60: 1 | APH60: 1 | API60: 1 | APJ60: 1 | APK60: 1 | APL60: 1 | APM60: 1 | APN60: 1 | APO60: 1 | APP60: 1 | APQ60: 1 | APR60: 1 | APS60: 1 | APT60: 1 | APU60: 1 | APV60: 1 | APW60: 1 | APX60: 1 | APY60: 1 | APZ60: 1 | AQA60: 1 | AQB60: 1 | AQC60: 1 | AQD60: 1 | AQE60: 1 | AQF60: 1 | AQG60: 1 | AQH60: 1 | AQI60: 1 | AQJ60: 1 | AQK60: 1 | AQL60: 1 | AQM60: 1 | AQN60: 1 | AQO60: 1 | AQP60: 1 | AQQ60: 1 | AQR60: 1 | AQS60: 1 | AQT60: 1 | AQU60: 1 | AQV60: 1 | AQW60: 1 | AQX60: 1 | AQY60: 1 | AQZ60: 1 | ARA60: 1 | ARB60: 1 | ARC60: 1 | ARD60: 1 | ARE60: 1 | ARF60: 1 | ARG60: 1 | ARH60: 1 | ARI60: 1 | ARJ60: 1 | ARK60: 1 | ARL60: 1 | ARM60: 1 | ARN60: 1 | ARO60: 1 | ARP60: 1 | ARQ60: 1 | ARR60: 1 | ARS60: 1 | ART60: 1 | ARU60: 1 | ARV60: 1 | ARW60: 1 | ARX60: 1 | ARY60: 1 | ARZ60: 1 | ASA60: 1 | ASB60: 1 | ASC60: 1 | ASD60: 1 | ASE60: 1 | ASF60: 1 | ASG60: 1 | ASH60: 1 | ASI60: 1 | ASJ60: 1 | ASK60: 1 | ASL60: 1 | ASM60: 1 | ASN60: 1 | ASO60: 1 | ASP60: 1 | ASQ60: 1 | ASR60: 1 | ASS60: 1 | AST60: 1 | ASU60: 1 | ASV60: 1 | ASW60: 1 | ASX60: 1 | ASY60: 1 | ASZ60: 1 | ATA60: 1 | ATB60: 1 | ATC60: 1 | ATD60: 1 | ATE60: 1 | ATF60: 1 | ATG60: 1 | ATH60: 1 | ATI60: 1 | ATJ60: 1 | ATK60: 1 | ATL60: 1 | ATM60: 1 | ATN60: 1 | ATO60: 1 | ATP60: 1 | ATQ60: 1 | ATR60: 1 | ATS60: 1 | ATT60: 1 | ATU60: 1 | ATV60: 1 | ATW60: 1 | ATX60: 1 | ATY60: 1 | ATZ60: 1 | AUA60: 1 | AUB60: 1 | AUC60: 1 | AUD60: 1 | AUE60: 1 | AUF60: 1 | AUG60: 1 | AUH60: 1 | AUI60: 1 | AUJ60: 1 | AUK60: 1 | AUL60: 1 | AUM60: 1 | AUN60: 1 | AUO60: 1 | AUP60: 1 | AUQ60: 1 | AUR60: 1 | AUS60: 1 | AUT60: 1 | AUU60: 1 | AUV60: 1 | AUW60: 1 | AUX60: 1 | AUY60: 1 | AUZ60: 1 | AVA60: 1 | AVB60: 1 | AVC60: 1 | AVD60: 1 | AVE60: 1 | AVF60: 1 | AVG60: 1 | AVH60: 1 | AVI60: 1 | AVJ60: 1 | AVK60: 1 | AVL60: 1 | AVM60: 1 | AVN60: 1 | AVO60: 1 | AVP60: 1 | AVQ60: 1 | AVR60: 1 | AVS60: 1 | AVT60: 1 | AVU60: 1 | AVV60: 1 | AVW60: 1 | AVX60: 1 | AVY60: 1 | AVZ60: 1 | AWA60: 1 | AWB60: 1 | AWC60: 1 | AWD60: 1 | AWE60: 1 | AWF60: 1 | AWG60: 1 | AWH60: 1 | AWI60: 1 | AWJ60: 1 | AWK60: 1 | AWL60: 1 | AWM60: 1 | AWN60: 1 | AWO60: 1 | AWP60: 1 | AWQ60: 1 | AWR60: 1 | AWS60: 1 | AWT60: 1 | AWU60: 1 | AWV60: 1 | AWW60: 1 | AWX60: 1 | AWY60: 1 | AWZ60: 1 | AXA60: 1 | AXB60: 1 | AXC60: 1 | AXD60: 1 | AXE60: 1 | AXF60: 1 | AXG60: 1 | AXH60: 1 | AXI60: 1 | AXJ60: 1 | AXK60: 1 | AXL60: 1 | AXM60: 1 | AXN60: 1 | AXO60: 1 | AXP60: 1 | AXQ60: 1 | AXR60: 1 | AXS60: 1 | AXT60: 1 | AXU60: 1 | AXV60: 1 | AXW60: 1 | AXX60: 1 | AXY60: 1 | AXZ60: 1 | AYA60: 1 | AYB60: 1 | AYC60: 1 | AYD60: 1 | AYE60: 1 | AYF60: 1 | AYG60: 1 | AYH60: 1 | AYI60: 1 | AYJ60: 1 | AYK60: 1 | AYL60: 1 | AYM60: 1 | AYN60: 1 | AYO60: 1 | AYP60: 1 | AYQ60: 1 | AYR60: 1 | AYS60: 1 | AYT60: 1 | AYU60: 1 | AYV60: 1 | AYW60: 1 | AYX60: 1 | AYY60: 1 | AYZ60: 1 | AZA60: 1 | AZB60: 1 | AZC60: 1 | AZD60: 1 | AZE60: 1 | AZF60: 1 | AZG60: 1 | AZH60: 1 | AZI60: 1 | AZJ60: 1 | AZK60: 1 | AZL60: 1 | AZM60: 1 | AZN60: 1 | AZO60: 1 | AZP60: 1 | AZQ60: 1 | AZR60: 1 | AZS60: 1 | AZT60: 1 | AZU60: 1 | AZV60: 1 | AZW60: 1 | AZX60: 1 | AZY60: 1 | AZZ60: 1 | BAA60: 1 | BAB60: 1 | BAC60: 1 | BAD60: 1 | BAE60: 1 | BAF60: 1 | BAG60: 1 | BAH60: 1 | BAI60: 1 | BAJ60: 1 | BAK60: 1 | BAL60: 1 | BAM60: 1 | BAN60: 1 | BAO60: 1 | BAP60: 1 | BAQ60: 1 | BAR60: 1 | BAS60: 1 | BAT60: 1 | BAU60: 1 | BAV60: 1 | BAW60: 1 | BAX60: 1 | BAY60: 1 | BAZ60: 1 | BBA60: 1 | BBB60: 1 | BBC60: 1 | BBD60: 1 | BBE60: 1 | BBF60: 1 | BBG60: 1 | BBH60: 1 | BBI60: 1 | BBJ60: 1 | BBK60: 1 | BBL60: 1 | BBM60: 1 | BBN60: 1 | BBO60: 1 | BBP60: 1 | BBQ60: 1 | BBR60: 1 | BBS60: 1 | BBT60: 1 | BBU60: 1 | BBV60: 1 | BBW60: 1 | BBX60: 1 | BBY60: 1 | BBZ60: 1 | BCA60: 1 | BCB60: 1 | BCC60: 1 | BCD60: 1 | BCE60: 1 | BCF60: 1 | BCG60: 1 | BCH60: 1 | BCI60: 1 | BCJ60: 1 | BCK60: 1 | BCL60: 1 | BCM60: 1 | BCN60: 1 | BCO60: 1 | BCP60: 1 | BCQ60: 1 | BCR60: 1 | BCS60: 1 | BCT60: 1 | BCU60: 1 | BCV60: 1 | BCW60: 1 | BCX60: 1 | BCY60: 1 | BCZ60: 1 | BDA60: 1 | BDB60: 1 | BDC60: 1 | BDD60: 1 | BDE60: 1 | BDF60: 1 | BDG60: 1 | BDH60: 1 | BDI60: 1 | BDJ60: 1 | BDK60: 1 | BDL60: 1 | BDM60: 1 | BDN60: 1 | BDO60: 1 | BDP60: 1 | BDQ60: 1 | BDR60: 1 | BDS60: 1 | BDT60: 1 | BDU60: 1 | BDV60: 1 | BDW60: 1 | BDX60: 1 | BDY60: 1 | BDZ60: 1 | BEA60: 1 | BEB60: 1 | BEC60: 1 | BED60: 1 | BEE60: 1 | BEF60: 1 | BEG60: 1 | BEH60: 1 | BEI60: 1 | BEJ60: 1 | BEK60: 1 | BEL60: 1 | BEM60: 1 | BEN60: 1 | BEO60: 1 | BEP60: 1 | BEQ60: 1 | BER60: 1 | BES60: 1 | BET60: 1 | BEU60: 1 | BEV60: 1 | BEW60: 1 | BEX60: 1 | BEY60: 1 | BEZ60: 1 | BFA60: 1 | BFB60: 1 | BFC60: 1 | BFD60: 1 | BFE60: 1 | BFF60: 1 | BFG60: 1 | BFH60: 1 | BFI60: 1 | BFJ60: 1 | BFK60: 1 | BFL60: 1 | BFM60: 1 | BFN60: 1 | BFO60: 1 | BFP60: 1 | BFQ60: 1 | BFR60: 1 | BFS60: 1 | BFT60: 1 | BFU60: 1 | BFV60: 1 | BFW60: 1 | BFX60: 1 | BFY60: 1 | BFZ60: 1 | BGA60: 1 | BGB60: 1 | BGC60: 1 | BGD60: 1 | BGE60: 1 | BGF60: 1 | BGG60: 1 | BGH60: 1 | BGI60: 1 | BGJ60: 1 | BGK60: 1 | BGL60: 1 | BGM60: 1 | BGN60: 1 | BGO60: 1 | BGP60: 1 | BGQ60: 1 | BGR60: 1 | BGS60: 1 | BGT60: 1 | BGU60: 1 | BGV60: 1 | BGW60: 1 | BGX60: 1 | BGY60: 1 | BGZ60: 1 | BHA60: 1 | BHB60: 1 | BHC60: 1 | BHD60: 1 | BHE60: 1 | BHF60: 1 | BHG60: 1 | BHH60: 1 | BHI60: 1 | BHJ60: 1 | BHK60: 1 | BHL60: 1 | BHM60: 1 | BHN60: 1 | BHO60: 1 | BHP60: 1 | BHQ60: 1 | BHR60: 1 | BHS60: 1 | BHT60: 1 | BHU60: 1 | BHV60: 1 | BHW60: 1 | BHX60: 1 | BHY60: 1 | BHZ60: 1 | BIA60: 1 | BIB60: 1 | BIC60: 1 | BID60: 1 | BIE60: 1 | BIF60: 1 | BIG60: 1 | BIH60: 1 | BII60: 1 | BIJ60: 1 | BIK60: 1 | BIL60: 1 | BIM60: 1 | BIN60: 1 | BIO60: 1 | BIP60: 1 | BIQ60: 1 | BIR60: 1 | BIS60: 1 | BIT60: 1 | BIU60: 1 | BIV60: 1 | BIW60: 1 | BIX60: 1 | BIY60: 1 | BIZ60: 1 | BJA60: 1 | BJB60: 1 | BJC60: 1 | BJD60: 1 | BJE60: 1 | BJF60: 1 | BJG60: 1 | BJH60: 1 | BJI60: 1 | BJJ60: 1 | BJK60: 1 | BJL60: 1 | BJM60: 1 | BJN60: 1 | BJO60: 1 | BJP60: 1 | BJQ60: 1 | BJR60: 1 | BJS60: 1 | BJT60: 1 | BJU60: 1 | BJV60: 1 | BJW60: 1 | BJX60: 1 | BJY60: 1 | BJZ60: 1 | BKA60: 1 | BKB60: 1 | BKC60: 1 | BKD60: 1 | BKE60: 1 | BKF60: 1 | BKG60: 1 | BKH60: 1 | BKI60: 1 | BKJ60: 1 | BKK60: 1 | BKL60: 1 | BKM60: 1 | BKN60: 1 | BKO60: 1 | BKP60: 1 | BKQ60: 1 | BKR60: 1 | BKS60: 1 | BKT60: 1 | BKU60: 1 | BKV60: 1 | BKW60: 1 | BKX60: 1 | BKY60: 1 | BKZ60: 1 | BLA60: 1 | BLB60: 1 | BLC60: 1 | BLD60: 1 | BLE60: 1 | BLF60: 1 | BLG60: 1 | BLH60: 1 | BLI60: 1 | BLJ60: 1 | BLK60: 1 | BLL60: 1 | BLM60: 1 | BLN60: 1 | BLO60: 1 | BLP60: 1 | BLQ60: 1 | BLR60: 1 | BLS60: 1 | BLT60: 1 | BLU60: 1 | BLV60: 1 | BLW60: 1 | BLX60: 1 | BLY60: 1 | BLZ60: 1 | BMA60: 1 | BMB60: 1 | BMC60: 1 | BMD60: 1 | BME60: 1 | BMF60: 1 | BMG60: 1 | BMH60: 1 | BMI60: 1 | BMJ60: 1 | BMK60: 1 | BML60: 1 | BMM60: 1 | BMN60: 1 | BMO60: 1 | BMP60: 1 | BMQ60: 1 | BMR60: 1 | BMS60: 1 | BMT60: 1 | BMU60: 1 | BMV60: 1 | BMW60: 1 | BMX60: 1 | BMY60: 1 | BMZ60: 1 | BNA60: 1 | BNB60: 1 | BNC60: 1 | BND60: 1 | BNE60: 1 | BNF60: 1 | BNG60: 1 | BNH60: 1 | BNI60: 1 | BNJ60: 1 | BNK60: 1 | BNL60: 1 | BNM60: 1 | BNN60: 1 | BNO60: 1 | BNP60: 1 | BNQ60: 1 | BNR60: 1 | BNS60: 1 | BNT60: 1 | BNU60: 1 | BNV60: 1 | BNW60: 1 | BNX60: 1 | BNY60: 1 | BNZ60: 1 | BOA60: 1 | BOB60: 1 | BOC60: 1 | BOD60: 1 | BOE60: 1 | BOF60: 1 | BOG60: 1 | BOH60: 1 | BOI60: 1 | BOJ60: 1 | BOK60: 1 | BOL60: 1 | BOM60: 1 | BON60: 1 | BOO60: 1 | BOP60: 1 | BOQ60: 1 | BOR60: 1 | BOS60: 1 | BOT60: 1 | BOU60: 1 | BOV60: 1 | BOW60: 1 | BOX60: 1 | BOY60: 1 | BOZ60: 1 | BPA60: 1 | BPB60: 1 | BPC60: 1 | BPD60: 1 | BPE60: 1 | BPF60: 1 | BPG60: 1 | BPH60: 1 | BPI60: 1 | BPJ60: 1 | BPK60: 1 | BPL60: 1 | BPM60: 1 | BPN60: 1 | BPO60: 1 | BPP60: 1 | BPQ60: 1 | BPR60: 1 | BPS60: 1 | BPT60: 1 | BPU60: 1 | BPV60: 1 | BPW60: 1 | BPX60: 1 | BPY60: 1 | BPZ60: 1 | BQA60: 1 | BQB60: 1 | BQC60: 1 | BQD60: 1 | BQE60: 1 | BQF60: 1 | BQG60: 1 | BQH60: 1 | BQI60: 1 | BQJ60: 1 | BQK60: 1 | BQL60: 1 | BQM60: 1 | BQN60: 1 | BQO60: 1 | BQP60: 1 | BQQ60: 1 | BQR60: 1 | BQS60: 1 | BQT60: 1 | BQU60: 1 | BQV60: 1 | BQW60: 1 | BQX60: 1 | BQY60: 1 | BQZ60: 1 | BRA60: 1 | BRB60: 1 | BRC60: 1 | BRD60: 1 | BRE60: 1 | BRF60: 1 | BRG60: 1 | BRH60: 1 | BRI60: 1 | BRJ60: 1 | BRK60: 1 | BRL60: 1 | BRM60: 1 | BRN60: 1 | BRO60: 1 | BRP60: 1 | BRQ60: 1 | BRR60: 1 | BRS60: 1 | BRT60: 1 | BRU60: 1 | BRV60: 1 | BRW60: 1 | BRX60: 1 | BRY60: 1 | BRZ60: 1 | BSA60: 1 | BSB60: 1 | BSC60: 1 | BSD60: 1 | BSE60: 1 | BSF60: 1 | BSG60: 1 | BSH60: 1 | BSI60: 1 | BSJ60: 1 | BSK60: 1 | BSL60: 1 | BSM60: 1 | BSN60: 1 | BSO60: 1 | BSP60: 1 | BSQ60: 1 | BSR60: 1 | BSS60: 1 | BST60: 1 | BSU60: 1 | BSV60: 1 | BSW60: 1 | BSX60: 1 | BSY60: 1 | BSZ60: 1 | BTA60: 1 | BTB60: 1 | BTC60: 1 | BTD60: 1 | BTE60: 1 | BTF60: 1 | BTG60: 1 | BTH60: 1 | BTI60: 1 | BTJ60: 1 | BTK60: 1 | BTL60: 1 | BTM60: 1 | BTN60: 1 | BTO60: 1 | BTP60: 1 | BTQ60: 1 | BTR60: 1 | BTS60: 1 | BTT60: 1 | BTU60: 1 | BTV60: 1 | BTW60: 1 | BTX60: 1 | BTY60: 1 | BTZ60: 1 | BUA60: 1 | BUB60: 1 | BUC60: 1 | BUD60: 1 | BUE60: 1 | BUF60: 1 | BUG60: 1 | BUH60: 1 | BUI60: 1 | BUJ60: 1 | BUK60: 1 | BUL60: 1 | BUM60: 1 | BUN60: 1 | BUO60: 1 | BUP60: 1 | BUQ60: 1 | BUR60: 1 | BUS60: 1 | BUT60: 1 | BUU60: 1 | BUV60: 1 | BUW60: 1 | BUX60: 1 | BUY60: 1 | BUZ60: 1 | BVA60: 1 | BVB60: 1 | BVC60: 1 | BVD60: 1 | BVE60: 1 | BVF60: 1 | BVG60: 1 | BVH60: 1 | BVI60: 1 | BVJ60: 1 | BVK60: 1 | BVL60: 1 | BVM60: 1 | BVN60: 1 | BVO60: 1 | BVP60: 1 | BVQ60: 1 | BVR60: 1 | BVS60: 1 | BVT60: 1 | BVU60: 1 | BVV60: 1 | BVW60: 1 | BVX60: 1 | BVY60: 1 | BVZ60: 1 | BWA60: 1 | BWB60: 1 | BWC60: 1 | BWD60: 1 | BWE60: 1 | BWF60: 1 | BWG60: 1 | BWH60: 1 | BWI60: 1 | BWJ60: 1 | BWK60: 1 | BWL60: 1 | BWM60: 1 | BWN60: 1 | BWO60: 1 | BWP60: 1 | BWQ60: 1 | BWR60: 1 | BWS60: 1 | BWT60: 1 | BWU60: 1 | BWV60: 1 | BWW60: 1 | BWX60: 1 | BWY60: 1 | BWZ60: 1 | BXA60: 1 | BXB60: 1 | BXC60: 1 | BXD60: 1 | BXE60: 1 | BXF60: 1979

Sheet Brand Sales Report
B2: Sum of Net Sales Amount | C2: Brand Name | H2: Sum of Net Sales (Cr) | I2: Column Labels
B3: Tractor Model Name | C3: Kubota | D3: Farmtrac | E3: Powertrac | F3: Grand Total | H3: Row Labels | I3: Kubota | J3: Farmtrac | K3: Powertrac | L3: Grand Total
B4: Kubota Mu4501 | C4: 7.7088347e+08 | F4: 7.7088347e+08 | H4: Kubota Mu4501 | I4: 77.088347 | L4: 77.088347
B5: Kubota Neostar | C5: 6.9232152e+08 | F5: 6.9232152e+08 | H5: Kubota Neostar | I5: 69.232152 | L5: 69.232152
B6: Farmtrac 60 | D6: 7.046158e+08 | F6: 7.046158e+08 | H6: Farmtrac 60 | J6: 70.46158 | L6: 70.46158
B7: Farmtrac 45 | D7: 7.5451749e+08 | F7: 7.5451749e+08 | H7: Farmtrac 45 | J7: 75.451749 | L7: 75.451749
B8: Powertrac 439 | E8: 8.556886e+08 | F8: 8.556886e+08 | H8: Powertrac 439 | K8: 85.56886 | L8: 85.56886
B9: Grand Total | C9: 1.463205e+09 | D9: 1.4591333e+09 | E9: 8.556886e+08 | F9: 3.7780269e+09 | H9: Grand Total | I9: 146.3205 | J9: 145.91333 | K9: 85.56886 | L9: 377.80269
B14: Sum of Quantity | C14: Model Name
B15: Region | C15: North | D15: East | E15: West | F15: South | G15: Grand Total
B16: Kubota Mu4501 | C16: 651 | D16: 371 | E16: 339 | F16: 397 | G16: 1758
B17: Kubota Neostar | C17: 694 | D17: 289 | E17: 291 | F17: 350 | G17: 1624
B18: Farmtrac 60 | C18: 708 | D18: 340 | E18: 329 | F18: 277 | G18: 1654
B19: Farmtrac 45 | C19: 745 | D19: 330 | E19: 409 | F19: 283 | G19: 1767
B20: Powertrac 439 | C20: 764 | D20: 517 | E20: 355 | F20: 280 | G20: 1916
B21: Grand Total | C21: 3562 | D21: 1847 | E21: 1723 | F21: 1587 | G21: 8719
B23: Sum of Net Sales Amount | C23: Model Name | J23: Sum of Net Sales (Cr) | K23: Column Labels
B24: Months | C24: Kubota Mu4501 | D24: Kubota Neostar | E24: Farmtrac 60 | F24: Farmtrac 45 | G24: Powertrac 439 | H24: Grand Total | J24: Row Labels | K24: Kubota Mu4501 | L24: Kubota Neostar | M24: Farmtrac 60 | N24: Farmtrac 45 | O24: Powertrac 439 | P24: Grand Total
B25: Jan | C25: 89184487 | D25: 90607022 | E25: 81032858 | F25: 71832025 | G25: 64437177 | H25: 3.9709357e+08 | J25: Jan | K25: 8.9184487 | L25: 9.0607022 | M25: 8.1032858 | N25: 7.1832025 | O25: 6.4437177 | P25: 39.709357
B26: Feb | C26: 94616034 | D26: 96491601 | E26: 59027769 | F26: 87761650 | G26: 80778380 | H26: 4.1867543e+08 | J26: Feb | K26: 9.4616034 | L26: 9.6491601 | M26: 5.9027769 | N26: 8.776165 | O26: 8.077838 | P26: 41.867543
B27: Mar | C27: 1.0071033e+08 | D27: 48218853 | E27: 71411025 | F27: 89900712 | G27: 1.1072471e+08 | H27: 4.2096563e+08 | J27: Mar | K27: 10.071033 | L27: 4.8218853 | M27: 7.1411025 | N27: 8.9900712 | O27: 11.072471 | P27: 42.096563
B28: Apr | C28: 66876066 | D28: 43134218 | E28: 79531475 | F28: 63464975 | G28: 1.2074806e+08 | H28: 3.7375479e+08 | J28: Apr | K28: 6.6876066 | L28: 4.3134218 | M28: 7.9531475 | N28: 6.3464975 | O28: 12.074806 | P28: 37.375479
B29: May | C29: 99517800 | D29: 95946952 | E29: 57726991 | F29: 65983517 | G29: 81797484 | H29: 4.0097274e+08 | J29: May | K29: 9.95178 | L29: 9.5946952 | M29: 5.7726991 | N29: 6.5983517 | O29: 8.1797484 | P29: 40.097274
B30: Jun | C30: 72242371 | D30: 47454721 | E30: 63459813 | F30: 67430388 | G30: 75540574 | H30: 3.2612787e+08 | J30: Jun | K30: 7.2242371 | L30: 4.7454721 | M30: 6.3459813 | N30: 6.7430388 | O30: 7.5540574 | P30: 32.612787
B31: Jul | C31: 17539547 | D31: 31845115 | E31: 61170837 | F31: 61735154 | G31: 52935544 | H31: 2.252262e+08 | J31: Jul | K31: 1.7539547 | L31: 3.1845115 | M31: 6.1170837 | N31: 6.1735154 | O31: 5.2935544 | P31: 22.52262
B32: Aug | C32: 44020811 | D32: 59448302 | E32: 39240013 | F32: 41646315 | G32: 51470553 | H32: 2.3582599e+08 | J32: Aug | K32: 4.4020811 | L32: 5.9448302 | M32: 3.9240013 | N32: 4.1646315 | O32: 5.1470553 | P32: 23.582599
B33: Sep | C33: 44758194 | D33: 50669629 | E33: 39089543 | F33: 53548721 | G33: 47350624 | H33: 2.3541671e+08 | J33: Sep | K33: 4.4758194 | L33: 5.0669629 | M33: 3.9089543 | N33: 5.3548721 | O33: 4.7350623 | P33: 23.541671
B34: Oct | C34: 43669030 | D34: 46322227 | E34: 56674240 | F34: 45804533 | G34: 35082514 | H34: 2.2755254e+08 | J34: Oct | K34: 4.366903 | L34: 4.6322227 | M34: 5.667424 | N34: 4.5804533 | O34: 3.5082514 | P34: 22.755254
B35: Nov | C35: 61251670 | D35: 44871995 | E35: 31193290 | F35: 64858130 | G35: 50607920 | H35: 2.52783e+08 | J35: Nov | K35: 6.125167 | L35: 4.4871995 | M35: 3.119329 | N35: 6.485813 | O35: 5.060792 | P35: 25.2783
B36: Dec | C36: 36497125 | D36: 37310885 | E36: 65057947 | F36: 40551372 | G36: 84215067 | H36: 2.636324e+08 | J36: Dec | K36: 3.6497125 | L36: 3.7310885 | M36: 6.5057947 | N36: 4.0551372 | O36: 8.4215067 | P36: 26.36324
B37: Grand Total | C37: 7.7088347e+08 | D37: 6.9232152e+08 | E37: 7.046158e+08 | F37: 7.5451749e+08 | G37: 8.556886e+08 | H37: 3.7780269e+09 | J37: Grand Total | K37: 77.088347 | L37: 69.232152 | M37: 70.46158 | N37: 75.451749 | O37: 85.56886 | P37: 377.80269
B40: Sum of Quantity | C40: Model Name
B41: Months | C41: Kubota | D41: Farmtrac | E41: Powertrac | F41: Grand Total | J41: Dealers Name | K41: Sum of Net Sales (Cr) | L41: Percentage of Net sales
B42: Jan | C42: 435 | D42: 375 | E42: 165 | F42: 975 | J42: Agri | K42: 70.991519 | L42: 0.18790634
B43: Feb | C43: 433 | D43: 341 | E43: 177 | F43: 951 | J43: Green Field | K43: 78.547505 | L43: 0.20790616
B44: Mar | C44: 332 | D44: 370 | E44: 220 | F44: 922 | J44: Kisan | K44: 77.553771 | L44: 0.20527586
B45: Apr | C45: 289 | D45: 322 | E45: 263 | F45: 874 | J45: Mahadev | K45: 79.482545 | L45: 0.2103811
B46: May | C46: 446 | D46: 318 | E46: 187 | F46: 951 | J46: Shakti | K46: 71.227348 | L46: 0.18853055
B47: Jun | C47: 271 | D47: 309 | E47: 183 | F47: 763 | J47: Grand Total | K47: 377.80269 | L47: 1
B48: Jul | C48: 117 | D48: 244 | E48: 119 | F48: 480
B49: Aug | C49: 221 | D49: 201 | E49: 115 | F49: 537
B50: Sep | C50: 201 | D50: 229 | E50: 100 | F50: 530
B51: Oct | C51: 199 | D51: 262 | E51: 101 | F51: 562
B52: Nov | C52: 241 | D52: 231 | E52: 109 | F52: 581
B53: Dec | C53: 197 | D53: 219 | E53: 177 | F53: 593
B54: Grand Total | C54: 3382 | D54: 3421 | E54: 1916 | F54: 8719
B57: Sum of Quantity | C57: Model Name
B58: Dealer Name | C58: Green Field | D58: Kisan | E58: Shakti | F58: Mahadev | G58: Agri | H58: Grand Total
B59: Kubota Mu4501 | C59: 388 | D59: 361 | E59: 340 | F59: 352 | G59: 317 | H59: 1758
B60: Kubota Neostar | C60: 326 | D60: 388 | E60: 321 | F60: 276 | G60: 313 | H60: 1624
B61: Farmtrac 60 | C61: 324 | D61: 290 | E61: 336 | F61: 358 | G61: 346 | H61: 1654
B62: Farmtrac 45 | C62: 368 | D62: 391 | E62: 312 | F62: 353 | G62: 343 | H62: 1767
B63: Powertrac 439 | C63: 391 | D63: 340 | E63: 424 | F63: 389 | G63: 372 | H63: 1916
B64: Grand Total | C64: 1797 | D64: 1770 | E64: 1733 | F64: 1728 | G64: 1691 | H64: 8719

Sheet Brand Sales Dashboard
E2: Escorts Tractors Sales Performance Dashboard
E5: Net Sales Amount | G5: Net Quantity Sold | I5: Total Orders | K5: AOV | M5: Average Discount
E7: =GETPIVOTDATA("Net Sales (Cr)",'Executive Sales Report'!$J$2) -> 377.80269 | G7: =GETPIVOTDATA("Quantity",'Executive Sales Report'!$B$12) -> 8719 | I7: =GETPIVOTDATA("Invoice ID",'Executive Sales Report'!$B$58) -> 1979 | K7: =(GETPIVOTDATA("Net Sales Amount",'Executive Sales Report'!$B$2))/GETPIVOTDATA("Invoice ID",'Executive Sales Report'!$B$58) -> 1909058.6 | M7: =GETPIVOTDATA("Discount %",'Master Sheet'!$B$16) -> 6.482567

Sheet Executive Sales Dashboard
E1: Executive Sales Performance Dashboard
E4: Net Sales Amount | G4: Net Quantity Sold | I4: Total Orders | K4: AOV | M4: Average Discount
E6: =GETPIVOTDATA("Net Sales (Cr)",'Executive Sales Report'!$J$2) -> 377.80269 | G6: =GETPIVOTDATA("Quantity",'Executive Sales Report'!$B$12) -> 8719 | I6: =GETPIVOTDATA("Invoice ID",'Executive Sales Report'!$B$58) -> 1979 | K6: =(GETPIVOTDATA("Net Sales Amount",'Executive Sales Report'!$B$2))/GETPIVOTDATA("Invoice ID",'Executive Sales Report'!$B$58) -> 1909058.6 | M6: =GETPIVOTDATA("Discount %",'Master Sheet'!$B$16) -> 6.482567
